{
  "contract": "0xe0f41a9626ade6c2bfaade6e497dc584bc3e9dc5",
  "era": 27,
  "developerReward": "1069669782996480000000",
  "stakers": [
    {
      "address": "VwLiPuRiYarBMFWBmzB7KU3Ku5x9GvqNSt4LQgNP2Dat3Qz",
      "stake": "500000000000000000000",
      "reward": "135763825945141987"
    },
    {
      "address": "VwhChd6gzaqAyC5NaNzmvwqXFiirkA5a8jyQ1KUxaoWBfN7",
      "stake": "428000000000000000000",
      "reward": "116213738738761071"
    },
    {
      "address": "VxKQJYPqPQhuF4haU4M2BGYy434f2KWo2Ak4Z2PjUhtrChH",
      "stake": "100000000000000000000",
      "reward": "27152765189028397"
    },
    {
      "address": "VxQZ21QghfTuASUcmV8tqdHikHntXFpW7F4M918N8td6Vcn",
      "stake": "800000000000000000000",
      "reward": "217222121512227180"
    },
    {
      "address": "VxRpiTuDwf5Qq4KCn8p51DPtDhZ8g6fikh2vxWAnTNYaLHw",
      "stake": "4445000000000000000000",
      "reward": "1206940238830972529"
    },
    {
      "address": "Vz7GTmytTEyJPAsiQYDvaP3WE9uA3b5Hi3iHrdY6yB85cQf",
      "stake": "101000000000000000000",
      "reward": "27424193896463754"
    },
    {
      "address": "VzKkA956wvwEsUFRzjMppYPpj62iNd6pBruaVLnuNREUbvu",
      "stake": "196000000000000000000",
      "reward": "53219280713423869"
    },
    {
      "address": "VzWPDqHSH69CEBU9isRqHsQGTUFkmUNgDHRD6k4YmWjxvWR",
      "stake": "101000000000000000000",
      "reward": "27424193896463754"
    },
    {
      "address": "VzWzJtZffe4h6gVGecPmmXh58xegmEdQrtzWo68iuPvUrmF",
      "stake": "2365000000000000000000",
      "reward": "642162883349649312"
    },
    {
      "address": "Vzp5mdKvN6h3ZzbcGrLTKWMXLtAZVc3UFd3oUQrzMsXatq5",
      "stake": "101000000000000000000",
      "reward": "27424193896463754"
    },
    {
      "address": "W18kBko6vQjGBzGJiM1sosmAM1rQxbgXomXVDhCh5he4hdm",
      "stake": "207000000000000000000",
      "reward": "56206066164995791"
    },
    {
      "address": "W1AVikaRe2CwrPwG3nDYRCegRgQ6VFXKA23v12h7mXCJsZu",
      "stake": "100000000000000000000",
      "reward": "27152765189028397"
    },
    {
      "address": "W1C55M6cqKEe6HKiDWQVtG23QNHTf8xzhSfVAXsznqUGgKw",
      "stake": "1200000000000000000000",
      "reward": "325833182268340769"
    },
    {
      "address": "W1CrpAoDYA3KvmEv27DeeujMEK4nRRNbqU4CRB1PmfHGW2n",
      "stake": "250000000000000000000",
      "reward": "67881779263848119"
    },
    {
      "address": "W2iovCCEN4b1zg8DhoYTpH9CPb53twdLadL4CbF6xzRsycf",
      "stake": "400000000000000000000",
      "reward": "108611060756113590"
    },
    {
      "address": "W3L7Xa9QAKiwP246Q4FhqjzcqD3nM95MThoos4wUYwfrevG",
      "stake": "101000000000000000000",
      "reward": "27424193896463754"
    },
    {
      "address": "W3dGuc6sKvsZ9yvkVNzrbKiTSk8Z5dGVkeD7qs2BX4nhuaH",
      "stake": "10832500000000000000000",
      "reward": "2941323416124787884"
    },
    {
      "address": "W5d8eZGSm9MZt9m9QRuzvJrDrrHGPpGiNScToEgPbnTDXD5",
      "stake": "120000000000000000000",
      "reward": "32583211259855777"
    },
    {
      "address": "W5rUBDfdzQLanK8d5R1joG9vB276KhaXuM78t74KHvRMVSd",
      "stake": "2000000000000000000000",
      "reward": "543055303780567949"
    },
    {
      "address": "W5y9pPYDESKnCAvcSwpUaSMUiZQzA4v32FKzUgACWaorMeW",
      "stake": "900000000000000000000",
      "reward": "244374886701255577"
    },
    {
      "address": "W6BEMXo74KgvMetkHSFoqbPrd53khrMHuFMtRfkPpvdFV5m",
      "stake": "100000000000000000000",
      "reward": "27152765189028397"
    },
    {
      "address": "W6HpbHmASd3YKAzfAPosJd3fA1h2arT3YEgRsi46KZXZ28Q",
      "stake": "200000000000000000000",
      "reward": "54305530378056795"
    },
    {
      "address": "W6TgwhHvtuESB5hRJSHYaeoH1iUHtrm5NvimuJjMXztzxEz",
      "stake": "935554793929647736580",
      "reward": "254028923910244558"
    },
    {
      "address": "W7yacJz2FxyBL5n3tMKUFB96EsbRmfApHACM1Qu8MU5Cr57",
      "stake": "366000000000000000000",
      "reward": "99379008276516720"
    },
    {
      "address": "W8PNq6oCAj6iAWodHyUm4eny9P4oocPZAK7xKH9VSmCjn1Y",
      "stake": "5000000000000000000000",
      "reward": "1357638259451419872"
    },
    {
      "address": "W8WRiw6xJKPsaYM1xpzvVmpYgcC65HySmWLJt4F7QMor58Z",
      "stake": "309000000000000000000",
      "reward": "83901956186340651"
    },
    {
      "address": "W8aG72c4Mn2CSykCXyomSAkodku37PnA7XsYbUxf1ZYza9B",
      "stake": "172798297891633818073",
      "reward": "46919460526466100"
    },
    {
      "address": "W8bdkEwwh2DZis7snCgq1CmJZuij3KF2Xr57wR8T8iqGQwn",
      "stake": "610000000000000000000",
      "reward": "165631680460861200"
    },
    {
      "address": "W8diUPj3mEvPvhSNS2bHUJSPhCTD69nCg9p479VaZhYJYtt",
      "stake": "256052840396273264777",
      "reward": "69525326885422211"
    },
    {
      "address": "WAXb2uB2BhTfC3SMKGQg6XMtqEfBgLXA1eq1AUpv8Z2KVuR",
      "stake": "660000000000000000000",
      "reward": "179208196764098273"
    },
    {
      "address": "WAZvfUQ1xLVr97QkPYKLQJGHT6ETAoGss5xmyUccwbdKMnk",
      "stake": "1000000000000000000000",
      "reward": "271527651890283974"
    },
    {
      "address": "WAzFSr3ZTJJETXvDMxEfKQ5JFXas27DVWGQhQPFjQnvKdzJ",
      "stake": "150000000000000000000",
      "reward": "40729014074819722"
    },
    {
      "address": "WBhPRFGp4kz3qUeLvwffk7TJDQLTTfXT2JVFeAGYZzQhJyi",
      "stake": "200000000000000000000",
      "reward": "54305530378056795"
    },
    {
      "address": "WD5wTBcEKdDEcepN7HzmiMBHk77GmYuJqp6VRPtw8q55Kda",
      "stake": "499000000000000000000",
      "reward": "135492129820260881"
    },
    {
      "address": "WDScFWrMSpDF6NvFNLZ3j4uiCNK9kPpm2iV6deGkSRSyEnE",
      "stake": "719000000000000000000",
      "reward": "195228373686590805"
    },
    {
      "address": "WDZ37UhQDVaa4WLPvY9cWVLorvWw1uFqaowMKaybN9MrWoU",
      "stake": "199513998634708765347",
      "reward": "54173426159856730"
    },
    {
      "address": "WDavWY74g9Ta6cFvxp3dhyuy6zsbyqELmCTcBcopMoCbMWL",
      "stake": "139000000000000000000",
      "reward": "37742228623247800"
    },
    {
      "address": "WDq9WKwrHx2gCpyAuJ7egpteS5MEuKv8X7c58EDXxnjwDN6",
      "stake": "123554613761471274891",
      "reward": "33548320821564351"
    },
    {
      "address": "WEKRuy5yiLZ3m9puBWtHVZ8yjo4S2byyo4T3nmqLZiEKnQh",
      "stake": "106000000000000000000",
      "reward": "28781872268532036"
    },
    {
      "address": "WFS3Tns219zcJDdVp97EPQzuptAGpfy3aiBjY7NagWCe2iR",
      "stake": "227500000000000000000",
      "reward": "61772360298263724"
    },
    {
      "address": "WFpJ7fbhiZQRBUR7RkskmhoPBw25yvcMXGiZAyej8CUXigt",
      "stake": "299000000000000000000",
      "reward": "81186599442204086"
    },
    {
      "address": "WFqn7ByJbSziGrd7XHGto7h2pESX9K5Xjh8FFCUuZjANN28",
      "stake": "101000000000000000000",
      "reward": "27424193896463754"
    },
    {
      "address": "WGJ83P8fhw9xcay7SBPT1258P6ty8Yj27qLSgFL96HBt4H1",
      "stake": "370000000000000000000",
      "reward": "100464990523703896"
    },
    {
      "address": "WGQ6hA5G51mcBXBd7XGWEBTLDtBZcRLpa5w8xtYh1AD1kJ3",
      "stake": "5000000000000000000000",
      "reward": "1357638259451419872"
    },
    {
      "address": "WGQHscu9CjkWvtusUL9XFUVTKBbzUrK9E3oS3hogWZRgGij",
      "stake": "880000000000000000000",
      "reward": "238944173212982448"
    },
    {
      "address": "WGZHjJUwWfRG7Lk4thA1xNSyaXZGBZrWHKUhHCzYRaYgvNd",
      "stake": "598489537180143246785",
      "reward": "162506372772391235"
    },
    {
      "address": "WGaXPqibyrHdnoApB9NN8NpHnQddhNpKBXrpasRjGwa5ZaP",
      "stake": "100000000000000000000",
      "reward": "27152765189028397"
    },
    {
      "address": "WGgd3RFP85kFQi3EPmEAdQts5YUgbgedPVL1WdoyBDxhfC7",
      "stake": "100000000000000000000",
      "reward": "27152765189028397"
    },
    {
      "address": "WHh8yGird1P1QgiCw6kmMbRpb5dTeyZy3LTwz2qVztKFLW4",
      "stake": "200000000000000000000",
      "reward": "54305530378056795"
    },
    {
      "address": "WJHFJStY3AkJmzdB9kTMXxMBJeowZheXvZ6amWaHZNGqvma",
      "stake": "1539000000000000000000",
      "reward": "417880941269645364"
    },
    {
      "address": "WJZVAfYbQAkxXjPJWVB7Xs29Q7zSGay2uHCA17SD8qpKE4f",
      "stake": "645500000000000000000",
      "reward": "175271009710333980"
    },
    {
      "address": "WJzrLWz5hpsGxX4Rd4mTwW5w1n6kA7uiHmN137hKBns5Xiy",
      "stake": "10000000000000000000000",
      "reward": "2715276518902839744"
    },
    {
      "address": "WKRMzwxRxSUy31iFgccPGDc3co6hJ9bPEEu936AcPHLhtmN",
      "stake": "107000000000000000000",
      "reward": "29053300975967393"
    },
    {
      "address": "WM6BK55omxAYMSF2LfhAzsRVscSxPAfXMbTfdhtY3fFdCpW",
      "stake": "801775400000000000000",
      "reward": "217704007749467094"
    },
    {
      "address": "WMHDDs7sCuPUos4BJTmqgKWZVbq7jExPPasStiuCoyQuznf",
      "stake": "1220330197245323500052",
      "reward": "331353213183494104"
    },
    {
      "address": "WML8DWgCqDw69JKTiPdEkQdXYBurYHGwWw6WyRCP5mBv4sj",
      "stake": "345000000000000000000",
      "reward": "93676866080808234"
    },
    {
      "address": "WMLnY3nfMK227t63xposQ5jSMPV2ikxkiwUKFDPVwJa3Qhg",
      "stake": "3170283661067113545104",
      "reward": "860819699458320520"
    },
    {
      "address": "WN7PiNm5sYDZW2mG1kqn4VUCz24Up2nmWYjzsuzfCsRucta",
      "stake": "513000000000000000000",
      "reward": "139293468811584622"
    },
    {
      "address": "WN7RUHeXgQ5kEmGpGvv9p7fr2Y5Fcg8YjfBLXnUdd2QnpbH",
      "stake": "501000000000000000000",
      "reward": "136035254652577344"
    },
    {
      "address": "WPXMhoLPM4SevCWVFWhBG9UCeyz45uVEeTgSp3bztpE3sNp",
      "stake": "100000000000000000000",
      "reward": "27152765189028397"
    },
    {
      "address": "WPeA2FtadbzCrzaudYB8xFeFNND48bmJgTE78SNvZLTJjmV",
      "stake": "432000000000000000000",
      "reward": "117299720985948248"
    },
    {
      "address": "WQhBWNE1b5FdmvtPDQiCaeYZwMg97mzB2iPJTBjTgCmqiQm",
      "stake": "500000000000000000000",
      "reward": "135763825945141987"
    },
    {
      "address": "WSN4QUVEQtWBeMdJ6Jp2qDxswLbJt9SNXhAccPnbsL8ddrz",
      "stake": "102000000000000000000",
      "reward": "27695622603899111"
    },
    {
      "address": "WT4F6szAiyp9T1LvvKrYZMgatjF4T1ZFe7DNh9uXMawo5Rr",
      "stake": "200000000000000000000",
      "reward": "54305530378056795"
    },
    {
      "address": "WT8ddSuPP1iq8gRfQcacHfCsf4itVWWpbM51eY7s5VR3A7b",
      "stake": "229842213263373936151",
      "reward": "62408278984255131"
    },
    {
      "address": "WTH1YDqn69hUKE1VRBG5GZrykovaB6yA6gLBj1LEcKKKy5h",
      "stake": "348000000000000000000",
      "reward": "94491419620560054"
    },
    {
      "address": "WUojMqV3Mip9Fk9i76SU6byNGYoAPohVLvuf9qZ8NJtf5uY",
      "stake": "11170000000000000000000",
      "reward": "3032963898356216569"
    },
    {
      "address": "WUszzZrmymsASemJqEAQEYHAwubsj5DdPC7Cw1sh659m6aa",
      "stake": "750000000000000000000",
      "reward": "203645605208990106"
    },
    {
      "address": "WUuxDYtvrsacwT5V38s8RTKZKpW75wh5sMuZ86m4MtyHQxJ",
      "stake": "100000000000000000000",
      "reward": "27152765189028397"
    },
    {
      "address": "WVJT4sSz1gc3idbJnWupbDA5aCNvevu9vLyMB7X12kVNBNU",
      "stake": "500812558532429643897",
      "reward": "135984445337885011"
    },
    {
      "address": "WVLofULBAjwP71EZciX5iUkzR9cLT4wvo3AfuKvtNz22wY8",
      "stake": "100000000000000000000",
      "reward": "27152765189028397"
    },
    {
      "address": "WVTVhQ8CLEaE3MiKNPqtPm11vNFW4Et4dt7QN3MoyewFZVW",
      "stake": "100000000000000000000",
      "reward": "27152765189028397"
    },
    {
      "address": "WVpYzGbWJXPcAV2AfnJH4g7t9UrYGo68S1vHLuFm4cyHM7s",
      "stake": "101000000000000000000",
      "reward": "27424193896463754"
    },
    {
      "address": "WVrLEF2Diopv7vS7vvd9q1WZeFA7jymE6AhZi3Y7ELCx1Lx",
      "stake": "1000000000000000000000",
      "reward": "271527651890283974"
    },
    {
      "address": "WVtJeF7t7PTmfjC5LzikL7cgCcPNDGsvkqQWZFYNTJfN8us",
      "stake": "104000000000000000000",
      "reward": "28238747436215574"
    },
    {
      "address": "WYGHp7PTSJtM3Gdwdc9WsurWX3YGHbuGDXrpoyCj31M7Gdw",
      "stake": "311000000000000000000",
      "reward": "84445081018657114"
    },
    {
      "address": "WYfVnuxMM8ziiZG6JBGRyRty1wc8YLhj5aiVauKCXWW43je",
      "stake": "252519580406775722547",
      "reward": "68565833090074368"
    },
    {
      "address": "WaJPC4HBghfsda3dYnrfhFkVe9338gy4cnNstQaKZ3sWkZx",
      "stake": "278700000000000000000",
      "reward": "75674591050423225"
    },
    {
      "address": "Wb9CgYZuQ8fhFhDig6Bp9dueRQnSv4jQocwTJQcYa2yNVGy",
      "stake": "139500000000000000000",
      "reward": "37878076685688353"
    },
    {
      "address": "Wcoidaetejx1SnusSBUiywLBhagVvRHFYekudf6i46iJ3Du",
      "stake": "400000000000000000000",
      "reward": "108611060756113590"
    },
    {
      "address": "Wcq2NkQj5HKLDcRYeRvcnD1dP5VmYemjv57DzFES1fDRzqU",
      "stake": "304653852261708503157",
      "reward": "82721842998249784"
    },
    {
      "address": "WdC1RrvrfDop1pqiDKAXRknPczYAxj6H1xccsShVdf1eK6H",
      "stake": "301764357647809349532",
      "reward": "81937240212421866"
    },
    {
      "address": "WdeX2T2btzgUe1Lk5qzyExEhDmWFP5QaT32WCR51qw9MJcV",
      "stake": "877000000000000000000",
      "reward": "238129619673230628"
    },
    {
      "address": "Wdwbi6FHXTWLkYtfxoEvn1JVK6N8U64LgYNq4cMXgBgJQfR",
      "stake": "33478000000000000000000",
      "reward": "9090203034838815049"
    },
    {
      "address": "WfidPcqUSBo8BbGRXtRGZYdJ7RaQGXjPyfzAj2sNbTXHcUz",
      "stake": "100000000000000000000",
      "reward": "27152765189028397"
    },
    {
      "address": "Wfu6YjjWyxu4YR7mB9DS7Dv8mTBUTKLtcwHEcLwnqTV6qLU",
      "stake": "658000000000000000000",
      "reward": "178665071931781811"
    },
    {
      "address": "Wg1dtAopSqECxxxkZjCDBUDE65WLcMKt9DWGvGvWaMXVzMS",
      "stake": "200000000000000000000",
      "reward": "54305530378056795"
    },
    {
      "address": "Wi1NgyhePQEYXaKf698NZGcshFTVN3YedGjeyDVwP1X717v",
      "stake": "750000000000000000000",
      "reward": "203645605208990106"
    },
    {
      "address": "Wi3TW1tnzvsCx7ZGEcdV1YRnEMACBYQV5Mckb4nMgYQ7JMT",
      "stake": "500000000000000000000",
      "reward": "135763825945141987"
    },
    {
      "address": "WiBkxapYfBSE6feDL7LY9iEz9SD7tL2qVWHNUVuVch8jDCg",
      "stake": "546000000000000000000",
      "reward": "148254092583746135"
    },
    {
      "address": "WibQYMKd3xyYqyB2YrrtQbDwqHVSbvqwx1y3o2MaZi1e9m1",
      "stake": "30533270688803252641915",
      "reward": "8290627546223403740"
    },
    {
      "address": "Wkt6B8VB3YQo8Cet3bupq5rcKRPNHHFGim9eJ1VA8PeVyrN",
      "stake": "5000000000000000000000",
      "reward": "1357638259451419872"
    },
    {
      "address": "WkyrEHBsooVJ7hH1ftcJjJpaph37nf4CCLzxNagcTMr9QGX",
      "stake": "101000000000000000000",
      "reward": "27424193896463754"
    },
    {
      "address": "WmT6FmJQXDVgXeKx1MudNodZKk3BbzhCMzYJNLfw76sdsSq",
      "stake": "353000000000000000000",
      "reward": "95849097992628336"
    },
    {
      "address": "WnrZbM2ZxNADpBvNGxVxX4pMEuHF1VSVJKkMWtiGAWNSRHG",
      "stake": "107000000000000000000",
      "reward": "29053300975967393"
    },
    {
      "address": "WocaEgng1eVGs9Wzgdi4M9Kmn5K9ErwyrkrNyLHj4WTGycK",
      "stake": "5350000000000000000000",
      "reward": "1452672803904296388"
    },
    {
      "address": "WovVWFt1dkNjEjvLF2hYKoLXzQsSPhSA2xDAH2YP5f6HoHo",
      "stake": "808000000000000000000",
      "reward": "219394353424047281"
    },
    {
      "address": "Wp2aziLwjhBrHi7roZdSpPupLE6Qq14XXvuyALBs7jtveDW",
      "stake": "365000000000000000000",
      "reward": "99107579569081363"
    },
    {
      "address": "WpK7kJwUnkBhHwig5g34vrjpnBx8XmDGvjnAqeD1FjfDCUm",
      "stake": "110000000000000000000000",
      "reward": "29868043312435911679"
    },
    {
      "address": "WqksWkKbpEoApcosMW7cWN12d3QUYgK8v23dLtr41DUUtti",
      "stake": "190000000000000000000",
      "reward": "51590173633920230"
    },
    {
      "address": "WrGRYy4tGxBpM8CnZQeo1xGPa1XupN34NCQoV9WVH8AJj2H",
      "stake": "100000000000000000000",
      "reward": "27152765189028397"
    },
    {
      "address": "Ws2jMnBpVD7wAuVmWfiWPeR2U7mHDvNP5G51KR6ZN2PeQgr",
      "stake": "100000000000000000000",
      "reward": "27152765189028397"
    },
    {
      "address": "Wty7YAoEr2YNKrA8FBwwuR4N6t4DJ5bZ5v8BnrKGPMLToP9",
      "stake": "260000000000000000000",
      "reward": "70597136007984684"
    },
    {
      "address": "WuMtbkuZyBF1c5rxrLJXZiHgf2ExydiYM8Jaecrt7ZJKhkh",
      "stake": "353000000000000000000",
      "reward": "95849097992628336"
    },
    {
      "address": "WuSTANhkhikbhfsifpeTW3dHvb4UotErkCCs7sLxxGfg57z",
      "stake": "200000000000000000000",
      "reward": "54305530378056795"
    },
    {
      "address": "WuWgcTrcCRf9zqBXQTfnvhmX9yjFDGJ2iBScaaNcBpbjiN9",
      "stake": "2095235665123622882864",
      "reward": "568914303367062104"
    },
    {
      "address": "Ww1yvL1FasQGJ97p5mQJq7txYDGfdyZk4ueq4hJBbSHJ5PZ",
      "stake": "100000000000000000000",
      "reward": "27152765189028397"
    },
    {
      "address": "WwMJuRi5Ecxj2BqWoeD5LKcim92wi4jz5K8zTBCQ5DD3nD6",
      "stake": "47590055697952517549573",
      "reward": "12922016650862679815"
    },
    {
      "address": "WxC2XbdKXT7o2N5vaR5XGrULQiyjFz2NuHTSekdePv7u5Y1",
      "stake": "100000000000000000000",
      "reward": "27152765189028397"
    },
    {
      "address": "WzMccMGVC1wdSPZzsKw6qNMY3h5szisAcM2tazJg6iUDNVd",
      "stake": "1062000000000000000000",
      "reward": "288362382352528326"
    },
    {
      "address": "WzTyFUWdKH7VxNMind77eGij8xhumzpmRUvZScN6JBbmenC",
      "stake": "150000000000000000000",
      "reward": "40729014074819722"
    },
    {
      "address": "WzfNw8PaDaAvMB2pufXHggNuM987pCHwbmWyPGGMLeckwmZ",
      "stake": "200000000000000000000",
      "reward": "54305530378056795"
    },
    {
      "address": "WznQUARPGiFyrYAyeCghRJs22WnAr6jqS9nSw7bvLdznv7f",
      "stake": "100000000000000000000",
      "reward": "27152765189028397"
    },
    {
      "address": "WzttMPTXm1G4BydrA4MEQcasBeJyegfBd199zmZnjtfL9iS",
      "stake": "110000000000000000000",
      "reward": "29867854515719213"
    },
    {
      "address": "X2j5G3Ezecs5ULGpYmBiUNHYt8VaLn7nCJzj4ttqx1bSDcu",
      "stake": "919174923717615705362",
      "reward": "249581236952545194"
    },
    {
      "address": "X4znYEA2KNApRZnaU1cAg5pjotyMMf71nY1xNw4hqj37tAC",
      "stake": "4500000000000000000000",
      "reward": "1221874433506277885"
    },
    {
      "address": "X564dpaTWa8xzvw7GMS7UqH65hzSvCiwv4hhd3MEzith5Fw",
      "stake": "100000000000000000000",
      "reward": "27152765189028397"
    },
    {
      "address": "X5MmzPKCe11CZk7pcxjHwYdEeWSH5B9Fmk4sub4vDUrqjo7",
      "stake": "10000000000000000000000",
      "reward": "2715276518902839744"
    },
    {
      "address": "X5cinGHZfYq9bcNKLYJKFZD6kcE5v631DppKCVFn4t8FgvR",
      "stake": "305000000000000000000",
      "reward": "82815706521707725"
    },
    {
      "address": "X5ydd8g22xYtWPD8YBtQmFnRG7Txy1zVJcTUmTDRESXrJWp",
      "stake": "362771486334908107120",
      "reward": "98502413889351105"
    },
    {
      "address": "X64UjmjPYNaSALDcTbyKNoaBaicAfvkDnjdFGaTq7Rmiw3F",
      "stake": "1459260329230419686895",
      "reward": "396229487774567864"
    },
    {
      "address": "X7ddSSVV1hvgivSgJBjrB9Pf8WMLk3w5FafHA5jTJz6eaoy",
      "stake": "2487000000000000000000",
      "reward": "675289219441821552"
    },
    {
      "address": "X7gJXaZsUWxCiv8DzGBFx2XQMfNBnKtLk7w3ErJxL7zyBkE",
      "stake": "101000000000000000000",
      "reward": "27424193896463754"
    },
    {
      "address": "X7jBuEL1Sb1rnCXwJxfwAKMtWQ4LP6mssBuPyyNDA3upR7T",
      "stake": "630000000000000000000",
      "reward": "171062393949134329"
    },
    {
      "address": "X7kRprJY1VBMGwu5ggAuHvMLupqfg9kcCLznEKZe4ef5vQN",
      "stake": "400000000000000000000",
      "reward": "108611060756113590"
    },
    {
      "address": "X7oM2jYJWBzutTKAAiZ6Mby3igxUErYoT7xH9MKLcaBX9gr",
      "stake": "100000000000000000000",
      "reward": "27152765189028397"
    },
    {
      "address": "X7oyKLG9wavM7TyY2UsvuRN9wTNsQqJVYLtvcfjAMPXss91",
      "stake": "100000000000000000000",
      "reward": "27152765189028397"
    },
    {
      "address": "X8AegVsbNtufBE86byGQ15CZBDXfNCsspryyEhLLErUQ7su",
      "stake": "199000000000000000000",
      "reward": "54033834253175689"
    },
    {
      "address": "X8YNPQA4aexmUZ4Y2uLvMqZuHzkGZTmPdfDQuap6E6cbNjf",
      "stake": "117000000000000000000",
      "reward": "31768657720103958"
    },
    {
      "address": "XAFnSMz6pge33AVHhgFucAk2ughooRUUjwLBCgmU3au9j5W",
      "stake": "599000000000000000000",
      "reward": "162644895009289279"
    },
    {
      "address": "XAkF5N9bW4wQaQ4fNChenpxYQ9S1msWhRY8uyuQTYJwvELU",
      "stake": "500000000000000000000",
      "reward": "135763825945141987"
    },
    {
      "address": "XBAX6f9LjFPk81tvJHmuEWdhaNRmACNGnGTsXu8YC9AQ36J",
      "stake": "300000000000000000000",
      "reward": "81458295567085192"
    },
    {
      "address": "XBGsbVavfwW2tFJr3U7gv4zhmApRY15QWurxMUfLVPZT8jd",
      "stake": "183000000000000000000",
      "reward": "49689370429535485"
    },
    {
      "address": "XCrqLN67JCv8K2T3NKrfMdpGuZUoouEEmnWaBQgau4ZFTaB",
      "stake": "100000000000000000000",
      "reward": "27152765189028397"
    },
    {
      "address": "XD82paKQAEccwsuKyeLTTXKTSPURKAwY3Fnnd8CiDWFVCvA",
      "stake": "250000000000000000000",
      "reward": "67881779263848119"
    },
    {
      "address": "XDfeUTNNh5Fc7FdJuxtxk3TeX8tY4FV34oDjMadHcKrNfxD",
      "stake": "102387672519738414445",
      "reward": "27800985077524264"
    },
    {
      "address": "XDta38NptLknGXymLAFkMRd3o9YFF1XhywWoLLpD9o9wthK",
      "stake": "1543500000000000000000",
      "reward": "419102771579273094"
    },
    {
      "address": "XDtgV1yo3sZ9NRoBCjoUWxeqqFqNPkGu7TepfTN7LTMTqcH",
      "stake": "123552945368236836695",
      "reward": "33547785986672853"
    },
    {
      "address": "XE22LgiHkoMCCyK9zsEdmkZJk7wkFQ5EnxvmvhPAfT4tKcr",
      "stake": "247000000000000000000",
      "reward": "67067225724096300"
    },
    {
      "address": "XFRs9assLoywYNUFGY521WzERMgUdqhmTLodm7fXxkzusB5",
      "stake": "2900000000000000000000",
      "reward": "787430190481823526"
    },
    {
      "address": "XFTewv8puYuzce9RBzJ7dMnDxorng7iju9fBjBst3TtsQVL",
      "stake": "995000000000000000000",
      "reward": "270169973518215692"
    },
    {
      "address": "XG6wsub8ZwML7473PU5VgVasvW238qWHCPVqAdp4rAC2ppB",
      "stake": "989340703234679460976",
      "reward": "268633125457495500"
    },
    {
      "address": "XJbBxfdZ5SR8FSjkR3xRoXqTE9LyYEDRVLYwTDwNaYF1PDC",
      "stake": "399000000000000000000",
      "reward": "108339364631232484"
    },
    {
      "address": "XJeJw9E6qxwPNfUYV97582tD24kgFk41LhREM9AD2EGrhDQ",
      "stake": "50000000000000000000000",
      "reward": "13576383396766535967"
    },
    {
      "address": "XJwWSGiZnFDirGfvqek7Km4E4Pv16Q7UF8fQbF4vowWUvHe",
      "stake": "123554615705418570282",
      "reward": "33548320821564351"
    },
    {
      "address": "XLh4uLcpFVx7KHgdoUnSgCEZjuQQe8ZBpowuk5FcBjaf7oo",
      "stake": "240000000000000000000",
      "reward": "65166422519711555"
    },
    {
      "address": "XLkr1WaSZ6u4DoMXqCy5VmsKQDRTHZsimwYSzfPo5a3NmPv",
      "stake": "300000000000000000000",
      "reward": "81458295567085192"
    },
    {
      "address": "XM6eXHALGTgJ5ygBJk6sH69AhmAGK8VA5LF3SL5Q9VThbhK",
      "stake": "1000000000000000000000",
      "reward": "271527651890283974"
    },
    {
      "address": "XMUC5yszne1avDW5wBPsi8pTRLb8TGfnRcBjKsBxVrFaU8q",
      "stake": "100000000000000000000",
      "reward": "27152765189028397"
    },
    {
      "address": "XMcWqqtHm9G2Bgq5bTvpP3w79uhh8ajmsqm2PtE8ZRQbQY7",
      "stake": "100000000000000000000",
      "reward": "27152765189028397"
    },
    {
      "address": "XPZhrU63FAMCuBD9KQu4jSM1VyS7oGh3RykzhFiGiMvJdoF",
      "stake": "140413256304291598864",
      "reward": "38125972657897788"
    },
    {
      "address": "XPw1jgFTHRrnu8EM4Jz2fDWzkS8D7RJbWSFErq1jbXg2dRA",
      "stake": "500000000000000000000",
      "reward": "135763825945141987"
    },
    {
      "address": "XQ9d55Rrgh4QrTTTRD8X4eVZq727Ck2N5dyS9gaNZjWka2R",
      "stake": "2000000000000000000000",
      "reward": "543055303780567949"
    },
    {
      "address": "XV6DGtyaVhMRZyNt94zFpUJBioPJqaWDJSJSU3APoCifqag",
      "stake": "100000000000000000000",
      "reward": "27152765189028397"
    },
    {
      "address": "XVHwXUSu8k33193Tj1frnwutiXWdMFyYTVWEkeKYsdhVrNj",
      "stake": "600000000000000000000",
      "reward": "162916591134170385"
    },
    {
      "address": "XXhoeAgo8DDg4sxgPfs7k31qRHzxNSPR8vTPhaSsbiqUz1r",
      "stake": "370000000000000000000",
      "reward": "100464990523703896"
    },
    {
      "address": "XXz3JWNFQkcHTX75WLo4iyxNRX7RT8ALFoYTnMmRuPCSiiL",
      "stake": "931000000000000000000",
      "reward": "252792118223654878"
    },
    {
      "address": "XavV8frc3nkbx7BAg8QiVrxDHkdR3PjpR3hcf8v46CcqcBD",
      "stake": "369986653468326039277",
      "reward": "100461514096909158"
    },
    {
      "address": "Xd5kBnGeEvCr9q3w8h8qatwrv8rDZy53bkAsqPcJGXmKzmz",
      "stake": "620000000000000000000",
      "reward": "168347037204997764"
    },
    {
      "address": "XdHpfHKvajPwdKoZM22zgc5CVhWsHWk7mNHPxfLQUHptKXJ",
      "stake": "650000000000000000000",
      "reward": "176492840019961709"
    },
    {
      "address": "XdSZHPoaahEuADUvQ6WPXDZeaVLPgCLp2gRXstAWNkqy9Bb",
      "stake": "150000000000000000000",
      "reward": "40729014074819722"
    },
    {
      "address": "XdUBBGKCLSSSLnLoVxjMhpHxz6dcb4ztdf8Xfmtika4vsg3",
      "stake": "2000000000000000000000",
      "reward": "543055303780567949"
    },
    {
      "address": "XdgqaFC4XMy5b615fUy3EgPifPGVaL3ikosHzXEhaP7soEB",
      "stake": "343000000000000000000",
      "reward": "93133741248491772"
    },
    {
      "address": "Xf95MFvUQh7R4uVPJhdKrmpbYAVJvN5qvG4KTRoeyfxXsz9",
      "stake": "935000000000000000000",
      "reward": "253878367888287804"
    },
    {
      "address": "XgWHpxQjSoEyrhnXchSoHa9WaVVWkMMpAypn73Tp9DFm48p",
      "stake": "235000000000000000000",
      "reward": "63808744147643272"
    },
    {
      "address": "Xhu7ZndWaxvPqeidFPcjVTBZ2wUfj5oscHBSxceudJia9PF",
      "stake": "300000000000000000000",
      "reward": "81458295567085192"
    },
    {
      "address": "Xi2x1JfB91FKoJmHJ6xescTPdxZkd18xffahj8fC2HKQhMb",
      "stake": "100000000000000000000",
      "reward": "27152765189028397"
    },
    {
      "address": "XiRPEbvQt22GpbX3aJVMrE2XPjnsH8cvnQfLGuRSTufT7E2",
      "stake": "844511147135365003799",
      "reward": "229308052972858658"
    },
    {
      "address": "XiXfcZxNzmxV7C1fADuvympAWFbc4N7JG9K7fagrjxBu3An",
      "stake": "403000000000000000000",
      "reward": "109425614295865409"
    },
    {
      "address": "XiePHvby6DSBKyDWpnDeCc53Bt2iutJ2CYod5uaw38S9PJC",
      "stake": "413647312026560815471",
      "reward": "112316664301859146"
    },
    {
      "address": "XjerrB5tv2MRvihvkffkgPuGRqFrrxhXuYBvgNemSq2pZSZ",
      "stake": "500000000000000000000",
      "reward": "135763825945141987"
    },
    {
      "address": "XkeX2NQdpgTbJdH6GibtLqStfTYuw1p4YZK6Vkb1yeD2tD9",
      "stake": "600000000000000000000",
      "reward": "162916591134170385"
    },
    {
      "address": "XkfZFKGStduyabr5izjyZaBNBTUGeGzK7ULuf1siLbnsxZk",
      "stake": "100000000000000000000",
      "reward": "27152765189028397"
    },
    {
      "address": "XkhJrZFoJAfzCHoJ9eiEWAW58Y3ehS9QNZ9vyMfXBcjwviS",
      "stake": "125000000000000000000",
      "reward": "33940889631924060"
    },
    {
      "address": "Xm6VzvybDCmXYPaG12eFkSut1pjhMYWJ8wbJVFzr1he27du",
      "stake": "300000000000000000000",
      "reward": "81458295567085192"
    },
    {
      "address": "XoD5jqnN6okaNQVegnEMHArW92b1SKszepsfpEcovcJi9yo",
      "stake": "100000000000000000000",
      "reward": "27152765189028397"
    },
    {
      "address": "XqpY3dmYH3oNfTfh6FtHvpkxAdDk1FzZBznrJg7dELx1FgS",
      "stake": "445000000000000000000",
      "reward": "120829631269836632"
    },
    {
      "address": "Xr5zYNHq4JQNMsyFPHNwbKdejBtg9cHJdm9smTkDqm3JW1Y",
      "stake": "234000000000000000000",
      "reward": "63537315440207916"
    },
    {
      "address": "XrEK7dQjHjqGo3EidpaciM7b9zf4q4A3qMc593cbAw7hsPD",
      "stake": "101000000000000000000",
      "reward": "27424193896463754"
    },
    {
      "address": "XtT8aQNCYCJDw53T3xt2WBh3ZYWY74AgrJfJkH493zN6YEg",
      "stake": "7678310000000000000000",
      "reward": "2084873585147453733"
    },
    {
      "address": "XtfizqFDPAePsgARguZ1ZhQWQLntZrPG3dmJMnJFGFxzaQh",
      "stake": "2000000000000000000000",
      "reward": "543055303780567949"
    },
    {
      "address": "XvDiyaPvBFgyH9rQKd1RsBuA9zDFTqWzBxjXSYU1wuAB6Gf",
      "stake": "466000000000000000000",
      "reward": "126531773465545117"
    },
    {
      "address": "XvhK28DMqEcuJFkzY8pRdLUYoyfdrYW2majsiLV14zJbC14",
      "stake": "300000000000000000000",
      "reward": "81458295567085192"
    },
    {
      "address": "XwEBvxjPJqR1v8KjoT3N5ftYPphHsr3eUTmYaSFBgcpfQiT",
      "stake": "600000000000000000000",
      "reward": "162916591134170385"
    },
    {
      "address": "XwvgcKUhGppo738CKB2ZLaJYDsPeWdiaTT2CLjSe4YsmPp7",
      "stake": "3000000000000000000000",
      "reward": "814582955670851923"
    },
    {
      "address": "XyY6AibvdpEnxbfTB3ATWUNEm1VVQ6Az7wmJ1ExGf6NhDn3",
      "stake": "100000000000000000000",
      "reward": "27152765189028397"
    },
    {
      "address": "XypZKQUqbk546eXDFUSrHzMoVaAGwwKMurL72HkirtrNVYH",
      "stake": "12187588300000000000000",
      "reward": "3309267358410134077"
    },
    {
      "address": "Xz96J37Esge2tA2ocuahdr5eX1LmvH5e4tf7ryfyYqLp2N7",
      "stake": "246615338501652532717",
      "reward": "66962665502808394"
    },
    {
      "address": "Y29tk9mr3m39gn97JJ1a9WxmmUcfik4KKYasbPFqQTcND9Y",
      "stake": "100000000000000000000",
      "reward": "27152765189028397"
    },
    {
      "address": "Y2GFSspKYBnRs8NRDSXdTLXG9Ke7mCvGEr6BcWb71xGmCLp",
      "stake": "998328756436347164476",
      "reward": "271073844484847718"
    },
    {
      "address": "Y2R4br5XAwFV7kqJfFJe62veaQQMjp6BC4QTwK2RLVDAiEk",
      "stake": "500000000000000000000",
      "reward": "135763825945141987"
    },
    {
      "address": "Y2h8x1ewsLSVNGNhGmtfuNMiTJsF1kDsKWQcE2kWQXNbm6k",
      "stake": "100000000000000000000",
      "reward": "27152765189028397"
    },
    {
      "address": "Y33yVVNtbfJuQivvasQiadhoEPDvL7poXKXoBpJHFQo7TPp",
      "stake": "100000000000000000000",
      "reward": "27152765189028397"
    },
    {
      "address": "Y5bFf1hGPwyYpDPd5698hQqFKPz2heM88uzoE9TGq2V2Lb7",
      "stake": "240000000000000000000",
      "reward": "65166422519711555"
    },
    {
      "address": "Y5c57mg3vHT4oz9po8Vwh8oTUkr7rkdJ2WMhxmCAMyYjS37",
      "stake": "10861000000000000000000",
      "reward": "2949061942169875918"
    },
    {
      "address": "Y7EfQ1qwHyj94ssJQRYsa2YMLswPcPJejs8FJXzAsBvdLoH",
      "stake": "110000000000000000000",
      "reward": "29867854515719213"
    },
    {
      "address": "Y7pnzQckNeHN8qHVK17eVVSFqAAq82ZdjSmsv9Su3ydLtcK",
      "stake": "135000000000000000000",
      "reward": "36655978958614875"
    },
    {
      "address": "Y83hJY29UByj9GnVvYvnAo5awG6rTurCZodSgK8cSz9ozMn",
      "stake": "800000000000000000000",
      "reward": "217222121512227180"
    },
    {
      "address": "Y9gdgx8Wv11sUk4ZyCVRydgxSAbsjoNx2d4ABYxF4Fhqu5u",
      "stake": "100000000000000000000",
      "reward": "27152765189028397"
    },
    {
      "address": "Y9ojHVZWvjj3weMQ5EDWmJd7EEEA7NWytpZQav2PhDsoGM9",
      "stake": "200000000000000000000",
      "reward": "54305530378056795"
    },
    {
      "address": "Y9zSV6xLh5STP71HLRgvDEu7oR3rTaSd4aiS5NEkP8Xg99N",
      "stake": "670000000000000000000",
      "reward": "181923286090789089"
    },
    {
      "address": "YB4MAU39fLfSzsUogHjWTKmzNEA4ax31WzxYRiABnYomoyF",
      "stake": "140000000000000000000",
      "reward": "38013657330683157"
    },
    {
      "address": "YCiik3VxgDJsV35kPqWkzfucJjcGT4U26F2ey3q21Q7KrVX",
      "stake": "100000000000000000000",
      "reward": "27152765189028397"
    },
    {
      "address": "YFD6PfBxGXk1i9VeAaMJ1J5XXMFsN5S5Z6n2w6CUEj8KToU",
      "stake": "200000000000000000000",
      "reward": "54305530378056795"
    },
    {
      "address": "YFdf6su5NTZpZJpJJ1TLDML2n2m6uVzpoWwm8iWVJjtoo6d",
      "stake": "100000000000000000000",
      "reward": "27152765189028397"
    },
    {
      "address": "YFonwVDBzGU11HNyMiyrRtGK6FiWf7zYy3zv3gLSaUKoYHj",
      "stake": "210000000000000000000",
      "reward": "57020619704747610"
    },
    {
      "address": "YFpHSY2NxzqPPoqG9LwaDUBMYCAfSg5LF6b1kFU8axubZPp",
      "stake": "100000000000000000000",
      "reward": "27152765189028397"
    },
    {
      "address": "YGACcpR78JeZ7H13w13FkjB1hZj9X21dUkDTN9Qk6xmvjbz",
      "stake": "190000000000000000000",
      "reward": "51590173633920230"
    },
    {
      "address": "YGB77429jqajwGGoGqhePdqbk46dMuuVfBRufeSiWPKXNeK",
      "stake": "302000000000000000000",
      "reward": "82001152981955906"
    },
    {
      "address": "YHsLzw27i4vMRMLigTeZ2gquxQp8orVuYKNDBoF5KY8q5Vb",
      "stake": "100000000000000000000",
      "reward": "27152765189028397"
    },
    {
      "address": "YJEAKXmUVK6yMHq9yPfQGX744cEXLN47oMasM75Pudyb7EH",
      "stake": "495000000000000000000",
      "reward": "134406147573073705"
    },
    {
      "address": "YJtEqwbmHCHw6MqojnLEdvUvdR2ufajDkLfQTvRsUexwUZo",
      "stake": "178171295303089246665",
      "reward": "48378222693027550"
    },
    {
      "address": "YJwGZ4paswvQBRKz1GHaURKmjaw1DtDPHxLVgSjJ1xciYTV",
      "stake": "100000000000000000000",
      "reward": "27152765189028397"
    },
    {
      "address": "YM3pvkjyJRnUfdHNmJyXMmcsq7uTszY9AtijAGxyPBaNnZX",
      "stake": "200000000000000000000",
      "reward": "54305530378056795"
    },
    {
      "address": "YMU4rSR2NKCpgFToZ3R9SxsqWgxVXwS1QgjX721d1tkjndA",
      "stake": "1000000000000000000000",
      "reward": "271527651890283974"
    },
    {
      "address": "YPL4p2z7xW3FG5HRnrEDwzGE1g14P3ftKczg6QPFJRzjVDT",
      "stake": "2000000000000000000000",
      "reward": "543055303780567949"
    },
    {
      "address": "YPjSdjyzVyuwW9tbyAaThyUG2ZJ7gVUvJg5iLkzyWHXTgBk",
      "stake": "800000000000000000000",
      "reward": "217222121512227180"
    },
    {
      "address": "YPyvuMSs8YCWhvBgVaYuczavHBmxdKXDNywkhq7mmRZoYeN",
      "stake": "326000000000000000000",
      "reward": "88517848717416211"
    },
    {
      "address": "YQAGUe3cLDSQxSEFwxSbjar1Q1t9gZjD5rokgcxKqVtHxu2",
      "stake": "6027588021958747273491",
      "reward": "1636656808832028196"
    },
    {
      "address": "YRfSXQ7bWPQmCHRQMGTGD9GJzgQ6y6TJ64YqbQKp4dqmKHP",
      "stake": "247110930058805338887",
      "reward": "67097443895465950"
    },
    {
      "address": "YS8PGt3bTkdLFxjNrTk8cuFZAgUMypzANGvD74jfDYFZYpw",
      "stake": "1000000000000000000000",
      "reward": "271527651890283974"
    },
    {
      "address": "YUPD1SRCBdaHqy1Eawpw4oCL2o3doY58yBWdBJDi1n5Cxde",
      "stake": "19000000000000000000000",
      "reward": "5159025653332841263"
    },
    {
      "address": "YUQLb9wfDT4kCG9Uz342qi8PDpjmPyqoTT7nrciwNmggk35",
      "stake": "6400000000000000000000",
      "reward": "1737776972097817436"
    },
    {
      "address": "YUxuD95yPmmPvvsY5Tf4QfP4ii7CjF4noPgBityrD7U6p3A",
      "stake": "2000000000000000000000",
      "reward": "543055303780567949"
    },
    {
      "address": "YV7Dr87xudJGnCp9DLnxPTn6vHergndvBcCjJWfUPQt2bf6",
      "stake": "2000000000000000000000",
      "reward": "543055303780567949"
    },
    {
      "address": "YV7YgwTD7aP6Vmn1eo8tEPiVawBPYLqfxVdAmmZBB94A86m",
      "stake": "210000000000000000000",
      "reward": "57020619704747610"
    },
    {
      "address": "YWo5dQwNFpCJJSRfC6n9bn8T45ggmu3WsbbJqwEffXecQwA",
      "stake": "120000000000000000000",
      "reward": "32583211259855777"
    },
    {
      "address": "YXwhSRcmjy8ZkdAcP1RxptZjPuX3grXxpKW9LJa6XXAYZSd",
      "stake": "1000000000000000000000",
      "reward": "271527651890283974"
    },
    {
      "address": "YY2W1Ui6tswQ9vMo1uWfyQ3oTkRb9uam5CoJzGY8Y2NLd7n",
      "stake": "253000000000000000000",
      "reward": "68696332803599939"
    },
    {
      "address": "YaXp7eLNzjKJAM97MCkAMWzozktUHuhngKpHSD61U86uAJU",
      "stake": "1300000000000000000000",
      "reward": "352985947457369167"
    },
    {
      "address": "YbgKTavafdNoZYraVL79xH8uRZK8CgC9sBAxALjDhVLWvd3",
      "stake": "105000000000000000000",
      "reward": "28510176143650931"
    },
    {
      "address": "YcU6b2JCdc2g5TyBPK6ruYy4SL7MxMgQMRtN8vmaXPne9Qf",
      "stake": "1596488383609538826185",
      "reward": "433490632412912997"
    },
    {
      "address": "Yd7Li7MnP1eUUCKBKachFWwwDCuZ1dwbhWAxTfWAcMC3jKN",
      "stake": "128000000000000000000",
      "reward": "34755443171675879"
    },
    {
      "address": "Yd8AtFYYL4aqwNm4stEoipYsDgVDNE69tExkrCkxpzwUFXJ",
      "stake": "132055137150861558314",
      "reward": "35856400795825006"
    },
    {
      "address": "YewJjiAQ4m8P9vHwGDUxuzwK8b8QsCq6LHG8UKVtcxkXHrg",
      "stake": "142000000000000000000",
      "reward": "38556782162999620"
    },
    {
      "address": "YewsBqRB8g9F9RcCLktuyvcQFT1xLoK16G4Nf1j822mtxD8",
      "stake": "627282917962161160428",
      "reward": "170324589216312507"
    },
    {
      "address": "YfrMMuTzfgqD4dbp1ARCdSTnXQhkfWbDDmnjxpSjNAQ86JP",
      "stake": "264000000000000000000",
      "reward": "71683118255171860"
    },
    {
      "address": "YfsSP5qPHsvGKqGqtwjEQ36qi3Je1g8cnPNWYahS96PYcPa",
      "stake": "2000000000000000000000",
      "reward": "543055303780567949"
    },
    {
      "address": "Ygr8Yfg2R6XgeuUp7eVu48Fix5NmYE9TDJUoK1wkhrrAv6D",
      "stake": "3000000000000000000000",
      "reward": "814582955670851923"
    },
    {
      "address": "YhKRnF1xSz7dGbm7GdVBRV5iC6gu9Nr9YXQPY2JHopGCrj2",
      "stake": "100000000000000000000",
      "reward": "27152765189028397"
    },
    {
      "address": "YhPgzAXsmQMmJQDFBWwKNxQ5BvcpJXEEGonEu3Kt8wMs7Bp",
      "stake": "7322000000000000000000",
      "reward": "1988125429702216856"
    },
    {
      "address": "YhtVEFNTav855ogVuYsjTij6j2J4Rry5fTE6e6u22LbFVM1",
      "stake": "200000000000000000000",
      "reward": "54305530378056795"
    },
    {
      "address": "Yhxdy9p3AdnRvrGZRwrSyg41Sf4Hd9yf8obZTdpUK8F2B58",
      "stake": "100000000000000000000",
      "reward": "27152765189028397"
    },
    {
      "address": "YjugF52jT2iFe96kuXNjUKac76iyYi71ZNQX2WaZHkczGLf",
      "stake": "100000000000000000000",
      "reward": "27152765189028397"
    },
    {
      "address": "YkkYigJ8m8Wzktrvj5yMdip27NBKMnJrAMW3QtpApQBsCLp",
      "stake": "100000000000000000000",
      "reward": "27152765189028397"
    },
    {
      "address": "Ym2WEHZLWKz6YgQBcDiMYtQKruXM6L4PGdjyEoVsx5Xe3n4",
      "stake": "100000000000000000000",
      "reward": "27152765189028397"
    },
    {
      "address": "Ym2X166BmPGa2fYSu1bkBXoZJXx6UQ1ZnQnyJmXaahq9faW",
      "stake": "309520475285292945027",
      "reward": "84043152597696186"
    },
    {
      "address": "Ymj7e9Jn3t5yGR89Xot6p1BVsAZAarrWXTKQmzVwF2wvuuw",
      "stake": "540000000000000000000",
      "reward": "146624718086796747"
    },
    {
      "address": "Yo2qDT6SKNZkqRYBoKsrNQjUkhvaSVLoBYFDgJbTypGXi4p",
      "stake": "100000000000000000000",
      "reward": "27152765189028397"
    },
    {
      "address": "Yo8RhLTHyNUMmsGYNegCfstVfBnCXiFd8qg8JEmyPtS8Pm2",
      "stake": "50200000000000000000000",
      "reward": "13630688927144592762"
    },
    {
      "address": "Yo9mxjWtiekceiqjEjoVocnsN8GLuiNKxAeFt9aR3DjFVTm",
      "stake": "1119000000000000000000",
      "reward": "303839434442704395"
    },
    {
      "address": "YoGy8prq4HAjebm5ZQrh9cKVb3NZTg8renhu5s2A8FiZ8ry",
      "stake": "396429054101768620441",
      "reward": "107641405097827281"
    },
    {
      "address": "YocgAWEnT2Z6JxmVkVSkCjF41EP6t6653nCCuhqGGRExCjf",
      "stake": "10450000000000000000000",
      "reward": "2837464095962190407"
    },
    {
      "address": "YqXtkm5NzymJKJvH9qinVaFuiT2FyysM8dfQ5m1dPmEUh8Q",
      "stake": "1990000000000000000000",
      "reward": "540339947036431384"
    },
    {
      "address": "Yqkoys953w7g8ZxqFyjmpfcJcACDXx2XN7XUKua8WbC4NKW",
      "stake": "100000000000000000000",
      "reward": "27152765189028397"
    },
    {
      "address": "YqnVq4SPvYioyZRgkQs1GkKYwGLsgmZfngRVf3ugtoqAdbX",
      "stake": "204000000000000000000",
      "reward": "55391512625243971"
    },
    {
      "address": "YqrTrNzyjP1gbw31DrpdHiLsxqCxTYbCNruQrR6FCXNxFeD",
      "stake": "215000000000000000000",
      "reward": "58378298076815892"
    },
    {
      "address": "Yr7ZxQJX6Ho4qBFywoA5hvFSxpBtLQv5T4LnLpzy3MffKJa",
      "stake": "2250000000000000000000",
      "reward": "610937083044416068"
    },
    {
      "address": "Yt3aLHKh2vVqo1TUMEUVzqrx6wWzwZQfoGNXk2Mh8VcjvcK",
      "stake": "1394000000000000000000",
      "reward": "378509338149448176"
    },
    {
      "address": "YvmU3XnGLXVqxDUpoJ6AWa4gme4BGDWbyLuQ1RFrQBYX5bG",
      "stake": "100000000000000000000",
      "reward": "27152765189028397"
    },
    {
      "address": "Yw4xc6BWdtAJR2TnhW4Qj8rP7nar3bpLfVacBg3cmkfmcv7",
      "stake": "106000000000000000000",
      "reward": "28781872268532036"
    },
    {
      "address": "Yw6zXcfMazuumMiYGjj6x3VUioKaSDfiNT6ybzRky6f8WAj",
      "stake": "1000000000000000000000",
      "reward": "271527651890283974"
    },
    {
      "address": "YwQjRoA4QDAN47HwthiQe2xwu99yheSgznYEjSWiym2Riw6",
      "stake": "300000000000000000000",
      "reward": "81458295567085192"
    },
    {
      "address": "YwVMeo7mGtPfPPQCTNzuAUaknyBJgoRYGnXcMHsysYUV881",
      "stake": "1400000000000000000000",
      "reward": "380138712646397564"
    },
    {
      "address": "YwYfMjWkfX8ybj5tJyxXYXdgQRzK1VfqAECEQJgHzMFJNq2",
      "stake": "394000000000000000000",
      "reward": "106981686259164202"
    },
    {
      "address": "YwaHNuhkREQGRqNBeMTMrMqmHLRck8EAmRrGu1VLEa6Jcf7",
      "stake": "2300000000000000000000",
      "reward": "624513599347653141"
    },
    {
      "address": "Ywdi8f25WikpJxB85QN3S2ZMVz7BLEttzidtqcbzYzvJUDf",
      "stake": "1100000000000000000000",
      "reward": "298680417079312372"
    },
    {
      "address": "YyQctcBnn34526pQ8j4SrspkKfK1pctTDYSS9dXG8te1kEd",
      "stake": "100000000000000000000",
      "reward": "27152765189028397"
    },
    {
      "address": "YyQqyZkVEyPnGg4tbWeTeCWDkCR17nYsvQHEuLF2aSLorQm",
      "stake": "150000000000000000000",
      "reward": "40729014074819722"
    },
    {
      "address": "YyrvDTrJ6Gj5zA8ZYasCCiqQZuR35ekUMyaxVbQCvdyGXFy",
      "stake": "200000000000000000000",
      "reward": "54305530378056795"
    },
    {
      "address": "Yz17mqvSgx17WD2GEsMk9snfViQMKxXhmz2pPbiDDx2zE2q",
      "stake": "200000000000000000000",
      "reward": "54305530378056795"
    },
    {
      "address": "YzDKqpsp7R1scMm1F4GRndhyuwF46p5QSHY7RUrnP7BsU9V",
      "stake": "520000000000000000000",
      "reward": "141194272015969367"
    },
    {
      "address": "Z1fHUw3G38sDiuJ8mGBGoiCJwyV5Qg2zdrNxzV49Drhf2ft",
      "stake": "100000000000000000000",
      "reward": "27152765189028397"
    },
    {
      "address": "Z27Tnw9q5rRW8khqzmtywSS3yZ6FuPkA53ycB6kyesxJzki",
      "stake": "224000000000000000000",
      "reward": "60821958696071351"
    },
    {
      "address": "Z2EfmyJ13Yw9ASuyhCzpggWsdw5sMp2spnXvVG7RWU4BhbR",
      "stake": "43700000000000000000000",
      "reward": "11865758922440301180"
    },
    {
      "address": "Z2MExNXmUJHQJAP1BSqHoHtEKDZimcoguiBVvJsZterE3Z7",
      "stake": "1512000000000000000000",
      "reward": "410549691994433240"
    },
    {
      "address": "Z2SCd7NiFx24GG4RCW1wPbsekXMdPagsJ5DcHa9yHDvw1B4",
      "stake": "183000000000000000000",
      "reward": "49689370429535485"
    },
    {
      "address": "Z2c2drAyi1uRJM7mBRu1cvN6hKk5Yt5J1WZ83rthmxS3u1G",
      "stake": "100000000000000000000",
      "reward": "27152765189028397"
    },
    {
      "address": "Z4ZbaGWmefJ7EBYqwCMUGBKn86aWSaU1tPhnm1FFYBFnTHH",
      "stake": "100000000000000000000",
      "reward": "27152765189028397"
    },
    {
      "address": "Z581vGPJ8gJH8Db1VnYQUnWi5dWAZqeEKpWEezjd83jcuPm",
      "stake": "100000000000000000000",
      "reward": "27152765189028397"
    },
    {
      "address": "Z5QuxNFx6QhHb49tNeScrWY9AxhzHV3dcuaoVDbeP4wh9JW",
      "stake": "883488509039743118045",
      "reward": "239891365805825831"
    },
    {
      "address": "Z78GYgi2sFdnta58DCeD1YALorg5XxqeyaHQHhJbqwrvc7g",
      "stake": "100000000000000000000",
      "reward": "27152765189028397"
    },
    {
      "address": "Z7F6Z51vg33bagqR8rKUWUqjwM2nuVSB8xy1gXd5gJaU3aq",
      "stake": "230000000000000000000",
      "reward": "62451333193020739"
    },
    {
      "address": "ZA9VQLDaAJtpNpTtejWrjM5yDx6CSRcMi4tZZmqLZmpnZ7g",
      "stake": "450000000000000000000",
      "reward": "122187309641904914"
    },
    {
      "address": "ZATcGzfaALJzFXFS6GcEpwZNuuM4M7MNFhQcDXpjLqrGqzy",
      "stake": "127000000000000000000",
      "reward": "34483747046794773"
    },
    {
      "address": "ZCGjxEe2Dtq8TLqwrrcrVLvnkocaq7BZUSLDkpYvmtD61L2",
      "stake": "1235000000000000000000",
      "reward": "335336663455372996"
    },
    {
      "address": "ZCKViX5oJtknWyVruus9nFFBYLHLvv6Cb6Xncfv4TBHxoQB",
      "stake": "369000000000000000000",
      "reward": "100193561816268540"
    },
    {
      "address": "ZCXVA2VjntX25uQemptNRKxce5CKp6S1fiHyj3HNpxj5VTx",
      "stake": "175000000000000000000",
      "reward": "47517138517715384"
    },
    {
      "address": "ZCcyzjwq4yf9PWBQtLtSS6cwUmwHSfe1aGFdTVQ1WzueJnj",
      "stake": "252000000000000000000",
      "reward": "68424904096164582"
    },
    {
      "address": "ZF1TkgxaCV8yH6yCpPzYNdHNRL6WB5tx36RfJa3NeUPszvL",
      "stake": "137000000000000000000",
      "reward": "37199103790931338"
    },
    {
      "address": "ZFjAyVeQ1BXhouqJBgxf96rgMHHj8KBZZkaJigywtDBxF9R",
      "stake": "294600000000000000000",
      "reward": "79992045712042767"
    },
    {
      "address": "ZFkkXQ3Gevr7GD23qmtSwZm6G8bczaJJgHVQTQkZUVUrftQ",
      "stake": "135000000000000000000",
      "reward": "36655978958614875"
    },
    {
      "address": "ZHzNAiWJ88Ck4QHFF5xmwTV7zuGBz9FPa3m7y22y2BCuAGe",
      "stake": "2000000000000000000000",
      "reward": "543055303780567949"
    },
    {
      "address": "ZJE1dDsNRu8T1B2iPwxDcVUWMcReY67xV6EVtDDN6Zm8haf",
      "stake": "440800000000000000000",
      "reward": "119689363281162384"
    },
    {
      "address": "ZJRuzbMrLg4qn7NG3D5VzaZTtLoxude8mXBhmspiWNva25c",
      "stake": "100000000000000000000",
      "reward": "27152765189028397"
    },
    {
      "address": "ZLabrYisfNrWUyjm2CokDDZbps1J7rDASBDWgBnXf3gdiwn",
      "stake": "188000000000000000000",
      "reward": "51047048801603768"
    },
    {
      "address": "ZM948EeGXxjfjuq7SCv4ncrE7tVnKtMUEbNmyCC7NUidMbo",
      "stake": "600000000000000000000",
      "reward": "162916591134170385"
    },
    {
      "address": "ZMHWDXx3T1FCjP7u3cvLAhj65CKjweYZn4dJ3EHrRmP2irp",
      "stake": "1000000000000000000000",
      "reward": "271527651890283974"
    },
    {
      "address": "ZNoEaiRKxiFsNBv8ySoQL7fnrJKbmntvbibds7VV3dm1sy4",
      "stake": "100000000000000000000",
      "reward": "27152765189028397"
    },
    {
      "address": "ZPZJoZtaGq18wRQJMzk9bmmFE7xSrzKFaM1zMW2Q61kTQaC",
      "stake": "1120000000000000000000",
      "reward": "304110863150139752"
    },
    {
      "address": "ZRLmsHQXsZSubffTT5VXFFu2yVnPmJPWCSxencAsDA6jSNK",
      "stake": "105000000000000000000",
      "reward": "28510176143650931"
    },
    {
      "address": "ZRjZGRGJ6YpLAm1Chk162Q5bCCZDgS7efS5Cj7ZCotcurji",
      "stake": "1000000000000000000000",
      "reward": "271527651890283974"
    },
    {
      "address": "ZS2Mw922xS6sEDvimixBQ4zz6g2btfv2jLfY6N22k6cQmtP",
      "stake": "100000000000000000000",
      "reward": "27152765189028397"
    },
    {
      "address": "ZUCSdGR9BL6oUBjHVGLPagyeq3XjRFDjuTRMo2QZ3sK7pTi",
      "stake": "123000000000000000000",
      "reward": "33397764799607597"
    },
    {
      "address": "ZWcYH1NZph5pfyQQjDL38ZwHZHzPGG4VgtbrsgevyVdqD2N",
      "stake": "200000000000000000000",
      "reward": "54305530378056795"
    },
    {
      "address": "ZWoQe19keS1H5QbabJ5yh7A4m7cgAdTv69CrgVAiNYofUm5",
      "stake": "136434128134818569510",
      "reward": "37045606177071343"
    },
    {
      "address": "ZWqgqX1d3EPnGF8M18TRGwikGjEKVTj2BPXfp7ZeHgxJuha",
      "stake": "2432960000000000000000",
      "reward": "660615756776121588"
    },
    {
      "address": "ZX2pe1F18PSsPvmWhTt5kChTrGh8JwnBAEvDuVTEoFxu4y3",
      "stake": "100000000000000000000",
      "reward": "27152765189028397"
    },
    {
      "address": "ZXTJXHZQusuHhebFbSK2fKUJAMw7vm6S46qZePp9nWSjU6j",
      "stake": "100000000000000000000",
      "reward": "27152765189028397"
    },
    {
      "address": "ZXZzKx3WnQhnmR2MDKgeZ7NqSCw6ddUUoy4urnrzLEfERLF",
      "stake": "1000000000000000000000",
      "reward": "271527651890283974"
    },
    {
      "address": "ZYMfVsQrKMLFWimPxGUg8brdzUNJzAoNhonPYvXPnqNAaX2",
      "stake": "130000000000000000000",
      "reward": "35298568003992342"
    },
    {
      "address": "ZYWnAfCenUTNPb3KuKRNhasqj7DcthXXoTRrmK4cwwHJmzK",
      "stake": "700000000000000000000",
      "reward": "190069356323198782"
    },
    {
      "address": "ZZYdbGA8zL9gJE7EcnLecuJX6E7L5hDhJht9zWF8uNqXjFM",
      "stake": "108700000000000000000",
      "reward": "29514863487330374"
    },
    {
      "address": "Za2Hia98MV3TyYemLNXspwjqy2Azee7XuoUcBYPbFT1bBGi",
      "stake": "693000000000000000000",
      "reward": "188168553118814037"
    },
    {
      "address": "ZbiExkW5rAM9RUUnokJKWKGV6fobLEEn99rPSXYXmGHWupu",
      "stake": "100000000000000000000",
      "reward": "27152765189028397"
    },
    {
      "address": "Zbqi66JFjpBc62WbkwUKgrgKwFKNYvtW5jdDLKz714Aq3nH",
      "stake": "500000000000000000000",
      "reward": "135763825945141987"
    },
    {
      "address": "ZbukCfqUATAmkB4gvYpwrthm53XMFMrcpGnSckQo1xCe754",
      "stake": "523751734765021891061",
      "reward": "142212865066827765"
    },
    {
      "address": "ZbyTGWtsK22suH54kAw2HdA4ypV3BDsFXsFiUNmJM4CMYNv",
      "stake": "217768137411428784053",
      "reward": "59130008516816669"
    },
    {
      "address": "ZcQusG4pfva3yWVqZdPJN5ufmMoC1wsLiwoSm1S4QXB1pCt",
      "stake": "100000000000000000000",
      "reward": "27152765189028397"
    },
    {
      "address": "ZcRNxFfPD6qJ1g96XTG7N7yVTDgbR2XYpCALsUxEg3vZMFA",
      "stake": "145000000000000000000",
      "reward": "39371335702751439"
    },
    {
      "address": "ZeaiixreYbFNm2C9ZTVGQ4sU6DGdQZ7Biod3R2ehs5YotWX",
      "stake": "100000000000000000000",
      "reward": "27152765189028397"
    },
    {
      "address": "Zg4WMWSkL5bzJhFH5cth69BKGbRVz6C65tAXW1Wwqmq2oZ6",
      "stake": "200000000000000000000",
      "reward": "54305530378056795"
    },
    {
      "address": "Zg6q2efsEhSUV64cQLiW7nUCVxHHkkreYTJiagdFsAFS7ZZ",
      "stake": "2100000000000000000000",
      "reward": "570208068969596346"
    },
    {
      "address": "Zh3oGzpUwzr7qVRUiQaC1CSYiYoY8BTMJN248ohmoyhMEej",
      "stake": "365000000000000000000",
      "reward": "99107579569081363"
    },
    {
      "address": "ZhAbsBd68ksxmP2XgX416YYYsHRJgSnu7XGX6UNv1jrkHfy",
      "stake": "123000000000000000000",
      "reward": "33397764799607597"
    },
    {
      "address": "ZhooSbU6rJxEFaTakKf1BpjmfEsYMkzLjdJ9z7uT6f7dZG5",
      "stake": "300000000000000000000",
      "reward": "81458295567085192"
    },
    {
      "address": "ZiFfR4XDfpYuYHxxhC1UE8mWjF45hvuvi7nSzYs16SNQ6Tp",
      "stake": "150000000000000000000",
      "reward": "40729014074819722"
    },
    {
      "address": "ZjvaqxUkt8sA9ou44crSKuTbL6JejdHrc8Lr2C8nusex5i1",
      "stake": "103900000000000000000",
      "reward": "28211470856749164"
    },
    {
      "address": "ZjyCs1iDL8XqJ98YeKHhBPpdYwXixkv8baWm6U8o31hmNnQ",
      "stake": "120000000000000000000",
      "reward": "32583211259855777"
    },
    {
      "address": "Zk89yfa2ojrPY4SXhHqPZUAGCVvEbpAXv7aMscFo7oCCxxH",
      "stake": "795455721375229228058",
      "reward": "215987990000094991"
    },
    {
      "address": "ZkLpWaAMe9CHtv7iHCWujvQfVaVnrs1aFCvF66MMZZof3HP",
      "stake": "100000000000000000000",
      "reward": "27152765189028397"
    },
    {
      "address": "ZkQoQiLJm9A3vmedeLz1kzA4xnAXE5ZHpogUrohhZMX2fNQ",
      "stake": "2000000000000000000000",
      "reward": "543055303780567949"
    },
    {
      "address": "ZnFqR8sPPjfAV84x4wyK8MBVPUwYfsiMcwzQL1HZgLW6rJ6",
      "stake": "262000000000000000000",
      "reward": "71139993422855397"
    },
    {
      "address": "ZnLDXzVdL592cvXZxv85bpnYfNT8ZBY9httToKaRVbgiXDo",
      "stake": "216000000000000000000",
      "reward": "58649726784251249"
    },
    {
      "address": "Zo7HmNGU54GH1qCzeZUp87GLHCzouFKXX1AtXPJgFhhTAte",
      "stake": "7909000000000000000000",
      "reward": "2147512110552498856"
    },
    {
      "address": "Zo8JoY7WEmJB9go6PQVscr2GMzFWE5rmWMn4bYLjQgtK6Re",
      "stake": "1055650000000000000000",
      "reward": "286638074662338000"
    },
    {
      "address": "ZoFGEbdiw31e9cdtcJUYKHEn5fHPxwZKRADY8M5CPxegULe",
      "stake": "105000000000000000000",
      "reward": "28510176143650931"
    },
    {
      "address": "ZoKn3RLfGmLy3QtRx6RhdjLnLT5idFAs67SpT1rRepuGhqo",
      "stake": "476000000000000000000",
      "reward": "129247130209681682"
    },
    {
      "address": "ZqBGkx6afVV6CF8krVLVqEYH2Pc3sftR7CxAD3xbGcFkVrb",
      "stake": "537000000000000000000",
      "reward": "145810164547044927"
    },
    {
      "address": "ZqtRPcBAauosbysmkgEeZgRYBZRcmp14C4gytnhcJf6SgCF",
      "stake": "9000000000000000000000",
      "reward": "2443748867012555770"
    },
    {
      "address": "ZrAYXMDBjLnqDh86w3wQfYfaRYNrc7EUcdiCcvwUDGQ2YWH",
      "stake": "500000000000000000000",
      "reward": "135763825945141987"
    },
    {
      "address": "ZsnkAgnmBZeTXKgM185oHhgX3A4epGpTgacNB4UrNcRP2By",
      "stake": "690000000000000000000",
      "reward": "187353999579062218"
    },
    {
      "address": "Zsvnb2uDd6xmbJzpkmapXQGBsYF7P3oeZm4gqXJS1GF5ZTL",
      "stake": "5000000000000000000000",
      "reward": "1357638259451419872"
    },
    {
      "address": "Zt32GF3XP2FENJJL6bM8eEdPPsJMAEYUenYjt6JR5rdkUMD",
      "stake": "100000000000000000000",
      "reward": "27152765189028397"
    },
    {
      "address": "ZtN2geCMJ7uwEyHd4dJc1x19q1Pcq8WC916aZALG4SBw2Fm",
      "stake": "4600000000000000000000",
      "reward": "1249027198695306282"
    },
    {
      "address": "ZtPsekJwTnSZoBmSkoSqLxFfwZuPYnSi4mdVcyminL1oL8g",
      "stake": "123300000000000000000",
      "reward": "33479327120561078"
    },
    {
      "address": "ZtVwhvW7zEqMHfa5S7VMMtcu8ghQwDwBjGEW37yq1joaR4q",
      "stake": "300000000000000000000",
      "reward": "81458295567085192"
    },
    {
      "address": "ZtpLoCTzqBcYV1BfYn6iKTficquk4R6PJTkei2vx1fCJfAP",
      "stake": "400366099777822167819",
      "reward": "108710272628486513"
    },
    {
      "address": "ZvBMX5SfudTNPoWGwvZSnF6EHkayN2g2knpXbwEnXADZmhF",
      "stake": "200000000000000000000",
      "reward": "54305530378056795"
    },
    {
      "address": "ZvKssGRs4VMV4cXt8zggPX5SedrRnyMhaiD4WsB37uQW8Kh",
      "stake": "1400000000000000000000",
      "reward": "380138712646397564"
    },
    {
      "address": "ZvWgyBa6G1KW1UYCrTvKDF4WCpu19dfiMR7R2rZ52FTZjUm",
      "stake": "2500000000000000000000",
      "reward": "678819129725709936"
    },
    {
      "address": "ZvXTvA9dQWmGuxTWbMhZM1nJ4kUwCoRhovrTsD4HNzg3Xsm",
      "stake": "100000000000000000000",
      "reward": "27152765189028397"
    },
    {
      "address": "ZveTpvKrCRpwZosB9KQhoNPDv55pULHgTrph5hdbZ4tWVed",
      "stake": "100000000000000000000",
      "reward": "27152765189028397"
    },
    {
      "address": "Zvu1G9oMxwGE2nS1ugt252LUgV1KZa1QeEHK2cWpkJ7jjxK",
      "stake": "345000000000000000000",
      "reward": "93676866080808234"
    },
    {
      "address": "ZvvStxHEUjiBhwg3hVH8eRSM3TsYRDpmHVZvdGPjikQv3hh",
      "stake": "2000000000000000000000",
      "reward": "543055303780567949"
    },
    {
      "address": "ZvzmV5tveF5PeefB64GpVmAWcPBozvEqVk8Hw718gJCR7gN",
      "stake": "116000000000000000000",
      "reward": "31496961595222852"
    },
    {
      "address": "ZxxynwAgQyiU7oT3yK63Y59wAr5PaHAHX3hK3trEvSAmMUP",
      "stake": "510632739971454967379",
      "reward": "138650864689449487"
    },
    {
      "address": "Zxyxbi5WYeSPcWh5VDqDfaBCXuVWCitofNHGEpwBDhzq1Fh",
      "stake": "500000000000000000000",
      "reward": "135763825945141987"
    },
    {
      "address": "ZyPwRZRxaegeA9FWTDGMGYX7hMuZNCsYTmMEsmwpcXq2eVi",
      "stake": "790000000000000000000",
      "reward": "214506764768090615"
    },
    {
      "address": "ZyspLXce1zmQWm3YLwsVYzwZ9wufVSibuf1VE3XDsrWNqze",
      "stake": "1600000000000000000000",
      "reward": "434444243024454359"
    },
    {
      "address": "a1XU2U4XHDsrBQELmMr8n9sVUna24riPHgM3tvsBnKE4HJk",
      "stake": "200000000000000000000",
      "reward": "54305530378056795"
    },
    {
      "address": "a1XZ98ioGkeGLEBs5pUy9psimfeeHr5ah829YnJ8TUSdW1F",
      "stake": "560000000000000000000",
      "reward": "152055431575069876"
    },
    {
      "address": "a1eQinbYPNxH4RvkBRWFdzDc9VHZrv4pPwPZNaGHiNDUQmG",
      "stake": "129000000000000000000",
      "reward": "35026871879111236"
    },
    {
      "address": "a2cs3P5hpe2L1MQhDCoDgYVFA3sd4jE755k2ZpaPkh3zdco",
      "stake": "100000000000000000000",
      "reward": "27152765189028397"
    },
    {
      "address": "a49YXYCMcLFVXjJipr5KG9yK9TkBDdkz26ZNLuokAwLqCRw",
      "stake": "500000000000000000000",
      "reward": "135763825945141987"
    },
    {
      "address": "a4U88eWCgA1xnwiZof6rL6Bi7nN1FdmUbreuixRzaqxSZyz",
      "stake": "790000000000000000000",
      "reward": "214506764768090615"
    },
    {
      "address": "a4Urhwc9RhF73sKyLukgTwJbWt2SWWUEXRisrfF7uyMAt39",
      "stake": "100000000000000000000",
      "reward": "27152765189028397"
    },
    {
      "address": "a4XX676FBaTAekrZD4RkRfqnsPGZpnFAxgbawdbawYWTEhc",
      "stake": "1500000000000000000000",
      "reward": "407291477835425962"
    },
    {
      "address": "a4vDGoqWWJQu7uj47oUrDRbNCJf47jFbngE3BgsvCNgBQu1",
      "stake": "1380000000000000000000",
      "reward": "374707999158124435"
    },
    {
      "address": "a4vmyKwiMdB5qU4ZQhHjcCDbU32EBgBxQEbWuN94qPep5qd",
      "stake": "700000000000000000000",
      "reward": "190069356323198782"
    },
    {
      "address": "a51DTA4KnMVcge4SifBj7qJzHV9c7qCHZgmMvQ4XzbSK5Lf",
      "stake": "400000000000000000000",
      "reward": "108611060756113590"
    },
    {
      "address": "a6aXBYhMQ1mNSw3RSKDJoDbqcEC771qnjQeRC3MoVWrtXDu",
      "stake": "230000000000000000000",
      "reward": "62451333193020739"
    },
    {
      "address": "a6ajjRgNBZBAePWv76aYMtQDEfauKX97RS4DphVX2Zdt1fm",
      "stake": "128518450548212144030",
      "reward": "34896104748139916"
    },
    {
      "address": "a7697urR1bFwkdu4979x9nP549ZbFUUrUDzu6JZuVEQAZVF",
      "stake": "110000000000000000000",
      "reward": "29867854515719213"
    },
    {
      "address": "a7EXb7u39iYHthRU5KSDAVgf12e98VTQGw9tw3bZGDntg8T",
      "stake": "714030000000000000000",
      "reward": "193878717837894996"
    },
    {
      "address": "a7LTef38YWEf1ru3wc67ZE9i2WMfrvHr1RcxbUH7d4B82Gv",
      "stake": "2334000000000000000000",
      "reward": "633745384409804262"
    },
    {
      "address": "a7QwQtdV5XYuCMvwPbHPT6X8yWKmDBBjRGKMzqM5232gRo1",
      "stake": "100000000000000000000",
      "reward": "27152765189028397"
    },
    {
      "address": "a7f4cDNW8DC6cCww2u8z3DMTrV9utiRjmCNcAi9SmiEDgtW",
      "stake": "1236998299561023592477",
      "reward": "335879253452797960"
    },
    {
      "address": "a9keUP9pNSc1qgTqAWXX6sdZCmHJmsFxrfQsQTcHLqNcW6V",
      "stake": "100000000000000000000",
      "reward": "27152765189028397"
    },
    {
      "address": "aA6jbRsrikoHdqCu2cRSqrS3ZT2MEnQSof4MhFvHci8j9a7",
      "stake": "100000000000000000000",
      "reward": "27152765189028397"
    },
    {
      "address": "aAJBPvqjFjXZLQBrHfyXZthiRLae6srN1q2MdbK9nxX3AvV",
      "stake": "236000000000000000000",
      "reward": "64080440272524378"
    },
    {
      "address": "aAKvEVeg1hKuLTJt93qGUASdXmkeNA5GaYiDi9Fc89LQ2CT",
      "stake": "215800000000000000000",
      "reward": "58595441042764178"
    },
    {
      "address": "aCFd7VwSC9JCe7SCy4Fz6DKmTXQVYrrFfsVUhSgirqKS9Gy",
      "stake": "400000000000000000000",
      "reward": "108611060756113590"
    },
    {
      "address": "aEW2vHwULbjnvqs4oCu7izNDFSwZCV3wa8bLRrnaActsnYR",
      "stake": "1400000000000000000000",
      "reward": "380138712646397564"
    },
    {
      "address": "aEiQ3jch2u1ht82NaKrzdK95ngMacBqRTRvdud76PxNHV5f",
      "stake": "201000000000000000000",
      "reward": "54576959085492152"
    },
    {
      "address": "aF1sawsUUhUxgsjiDtRq9VphtXhx399EUo7wfS26d7wQbdy",
      "stake": "100000000000000000000",
      "reward": "27152765189028397"
    },
    {
      "address": "aFeR3AEPamFLB4csPLCtJPgiT4rEwJTF8MRA1StFv4dPdGZ",
      "stake": "200000000000000000000",
      "reward": "54305530378056795"
    },
    {
      "address": "aHE4WC4ETKuw3cBZ2uDe3UGyZX1QRoar6nWRXFmFn57UbiT",
      "stake": "110000000000000000000",
      "reward": "29867854515719213"
    },
    {
      "address": "aHNY4jpxHcKWphgsCKrusanufDk7RC2VzdwyuPFn3fhZchE",
      "stake": "5000000000000000000000",
      "reward": "1357638259451419872"
    },
    {
      "address": "aNfw3tfY7GXMnRBgfzfHG4K3P5tfy8FCtovmRSuxLfNf2DE",
      "stake": "100000000000000000000",
      "reward": "27152765189028397"
    },
    {
      "address": "aNzmKXSmaqDVdHHZcAeLtJb9mjdVPJUHDpkhpqpXmnZS5hM",
      "stake": "250000000000000000000",
      "reward": "67881779263848119"
    },
    {
      "address": "aPTi6yAQqy5nAUUqsf7VYUgpDpn5VuR748ni9Y5RD762Kjb",
      "stake": "100000000000000000000",
      "reward": "27152765189028397"
    },
    {
      "address": "aPVbcsNAQjzCJH9YARZCVR1VWiSWSAePmvZDQQ1KxGWcoGZ",
      "stake": "784107026922628038114",
      "reward": "212906538772727881"
    },
    {
      "address": "aR5RwEqAGU9cGohYvQcf5yvPn8y2etWxpYwQ9AB8ShnhCCe",
      "stake": "200000000000000000000",
      "reward": "54305530378056795"
    },
    {
      "address": "aRCqxDuHS1vcFsYj3C6hdCPgx5sQszmBkZ1pNoJBhgXXH3r",
      "stake": "1249400000000000000000",
      "reward": "339246573929670879"
    },
    {
      "address": "aRzv5pRDMhDgdMLeKtUkKGDQKtYdqwtCSbzPHqm7Aku8NmT",
      "stake": "135000000000000000000",
      "reward": "36655978958614875"
    },
    {
      "address": "aTYMAoL7CuEoaXDUUd22jPcwPPZPHjvsRUh2cPnLfirS1qk",
      "stake": "733801769085281530269",
      "reward": "199247390478754330"
    },
    {
      "address": "aTeDvRSi1QEBH6n3nQGneCFbKY4EwzRpuCoZKJrtxeawEWx",
      "stake": "100000000000000000000",
      "reward": "27152765189028397"
    },
    {
      "address": "aTsLDvEAA7iaJctyp5kXpCK1xqfMJWuZUF8Gig1o8p9f674",
      "stake": "1818554606932936540953",
      "reward": "493787650662978826"
    },
    {
      "address": "aTtQxqntB2ZnfoD5dmfxg9GXoGCGAhsD3KxPnjLTjgrMTVZ",
      "stake": "100000000000000000000",
      "reward": "27152765189028397"
    },
    {
      "address": "aUZcnK6UrqsNVeXu3G7w5TaE2aXdSYs36JeH3xTti4hBGLk",
      "stake": "1000000000000000000000",
      "reward": "271527651890283974"
    },
    {
      "address": "aVjVRt7M8zdqLfvULEQ4Jm5XWSDLLX576UC5SNnZhGwzT3n",
      "stake": "100000000000000000000",
      "reward": "27152765189028397"
    },
    {
      "address": "aXDpbYKhMiZ5TM7XYvfk2WhK2MWR1atWCJVsjk3WzDCo8q6",
      "stake": "100000000000000000000",
      "reward": "27152765189028397"
    },
    {
      "address": "aXGQtTCDQqBVvCjtGb4Ab3JCzTT9jC4LByD4uDHFAZeKm74",
      "stake": "36000000000000000000000",
      "reward": "9774996002885114577"
    },
    {
      "address": "aXJqBRLdy25jSLz1BrSb7Wkcm9tqhVLVWqNwDQZTRPz11P7",
      "stake": "100000000000000000000",
      "reward": "27152765189028397"
    },
    {
      "address": "aXRLqMYZdCHQ8War6UnufjC4BstfwrdoEF1m17RCLeFB7Qo",
      "stake": "120000000000000000000",
      "reward": "32583211259855777"
    },
    {
      "address": "aYncxx3frCYRZY6yZKyJbLYuGNCBZ3mB7c76v8krnUU15Xf",
      "stake": "123000000000000000000",
      "reward": "33397764799607597"
    },
    {
      "address": "aYrL5ngNC6Uy3Yk23qYPeUh5DwQJkSED799r6EyetGtDEAx",
      "stake": "350000000000000000000",
      "reward": "95034544452876516"
    },
    {
      "address": "aZ91enMqBrNz5WZa5nYfeCvu2qpTL4NGkFTAAZTJybMyu6j",
      "stake": "3000000000000000000000",
      "reward": "814582955670851923"
    },
    {
      "address": "aZR37774CPYr2qnZxVFn29AcRYfxHYkDj9Xa33idPvEqyZJ",
      "stake": "128000000000000000000",
      "reward": "34755443171675879"
    },
    {
      "address": "aba98k9daZiGbxgbNSCn2NPGLsq1iuK5s9a5bdFLbf614EB",
      "stake": "100000000000000000000",
      "reward": "27152765189028397"
    },
    {
      "address": "ac8aX7c6hk8cAnWqzqJWSXT4VLVYjeWx3Ka7TJrQA2RBTZq",
      "stake": "100000000000000000000",
      "reward": "27152765189028397"
    },
    {
      "address": "achoMeo3up5NdpHsR3CtuAd9nUSmNLJsbwqweVpUxLgJYB7",
      "stake": "120000000000000000000",
      "reward": "32583211259855777"
    },
    {
      "address": "ae6MNDeNMdo8pJWNraSmUaWxAC5kcrryteY1u4adCPjeRxL",
      "stake": "400000000000000000000",
      "reward": "108611060756113590"
    },
    {
      "address": "ae91yTEpTJMeUDnk3G1QbQDtiZCuRBygMVDn7rKKWa3ShP2",
      "stake": "1024994992622440325037",
      "reward": "278314439245950891"
    },
    {
      "address": "aehPPnrHFd6B3jrSxtWBY2weS2wY4n3zd4qJN5RHKmnBiHk",
      "stake": "295000000000000000000",
      "reward": "80100617195016910"
    },
    {
      "address": "agvLKsJXqgJtfLHWm5Wti4WBaBqpmDP7KoRP2LwiRJLCdC4",
      "stake": "100000000000000000000",
      "reward": "27152765189028397"
    },
    {
      "address": "ahKk3F2ynSG9vHiaiWv6iRaxgbDLYTP3ieQcraQgcHSeTqh",
      "stake": "286000000000000000000",
      "reward": "77656689158315702"
    },
    {
      "address": "ahSDKG2ByZPLaNhjne3XHn3yjmr4XyzNKqpjER1XvstvtKt",
      "stake": "3200000000000000000000",
      "reward": "868888486048908718"
    },
    {
      "address": "aheVYZxYPQFN7cVxE5gz3cHFDTn27z1N7F9Yp5DWj8ww48m",
      "stake": "1812000000000000000000",
      "reward": "492007987561518432"
    },
    {
      "address": "ajnmRExmbjGKJYpoS1jKiBVqUQN59WEPnb3dC6Jc5DDER4q",
      "stake": "200000000000000000000",
      "reward": "54305530378056795"
    },
    {
      "address": "akK7VSyi2pnnVMsZcSKovwuuMon5trLmN6dEC2f5jJw2chq",
      "stake": "165000000000000000000",
      "reward": "44802049191024568"
    },
    {
      "address": "anXkTLbKqQVYnxeMTcAZ48uxp8Kn32mMtoJzvv6erhvSbjA",
      "stake": "105000000000000000000",
      "reward": "28510176143650931"
    },
    {
      "address": "ao5BfWGij3C9YwT4wScKM43C32mx1ToiaAwcww4WcKMwc9K",
      "stake": "100000000000000000000",
      "reward": "27152765189028397"
    },
    {
      "address": "aoA4DtjNjf5pJURmYjvMsTBhGSsJnKxpqr6HFtQC4WLcgKs",
      "stake": "550000000000000000000",
      "reward": "149340074830933311"
    },
    {
      "address": "aoBhkYcsbB7uHMyW2Y4sg5jzWTryrufsXAXmRcZCe2cnEjd",
      "stake": "100000000000000000000",
      "reward": "27152765189028397"
    },
    {
      "address": "apawTzWUqSxvuCReiWRErjfzEk2FuVT92UsijQxy7VPESEv",
      "stake": "147000000000000000000",
      "reward": "39914460535067902"
    },
    {
      "address": "aq3f2C3uKbu5UfnCu6sr8KwBDhd1K6ea8CdjVjsjYcmnZnM",
      "stake": "100000000000000000000",
      "reward": "27152765189028397"
    },
    {
      "address": "aqEPz9xzEtQGMXTEjo9PpM3HbWT975xFkP88C7Qf7z4ouNg",
      "stake": "138000000000000000000",
      "reward": "37470799915812444"
    },
    {
      "address": "aqMnapwNPeLx6Mx68Uzm1wcgTq7vxYF2cDys9nu9NgmgDSn",
      "stake": "5436820000000000000000",
      "reward": "1476246988834310062"
    },
    {
      "address": "aqdiUbdCi8viSWBogBgLJghuKpw4g3GmrEmCUeqvUafQu2c",
      "stake": "100000000000000000000",
      "reward": "27152765189028397"
    },
    {
      "address": "aqeZKeX61ESNoMTm4SHQq7y8kZLucJ8o3jSFe2iojdWp4qN",
      "stake": "500000000000000000000",
      "reward": "135763825945141987"
    },
    {
      "address": "aqjvdWiQhjA8CFUz7QT3gFJmSBZYh1vhm92k9UDMZD6U3FK",
      "stake": "100000000000000000000",
      "reward": "27152765189028397"
    },
    {
      "address": "aqt97NhgQACJsSwApn3yirJuL5fqRHDXm5WbuFTZgsrLmDg",
      "stake": "107500000000000000000",
      "reward": "29189149038407946"
    },
    {
      "address": "asowkNifxL6a1CZPT1xVdJe8yqUaAmaqx9mnrp5y3ktChfo",
      "stake": "100000000000000000000",
      "reward": "27152765189028397"
    },
    {
      "address": "atSArokQwyAdXdpu2oEo9AqqdBZgc8qYRuHLdt4f5UsC5aE",
      "stake": "503000000000000000000",
      "reward": "136578379484893807"
    },
    {
      "address": "av3FBpGnMtYCQdkhYLouq1EQmUV8FnBcHw1E5MJLZQ82E5d",
      "stake": "200000000000000000000",
      "reward": "54305530378056795"
    },
    {
      "address": "av6AYeM556wzE6ct1RKyCfTnZNXCfhWuxc93PVo7BWmXsMW",
      "stake": "1000000000000000000000",
      "reward": "271527651890283974"
    },
    {
      "address": "avgnqQcGS4GCjkYQtTgdYcwLab1kJ8LZxJ1hfbhdRX5GQMg",
      "stake": "200000000000000000000",
      "reward": "54305530378056795"
    },
    {
      "address": "axUsMNcQXWbf9zpPj4zDH3UZc4xy28yDHyGnUfavd7eD5qc",
      "stake": "366000000000000000000",
      "reward": "99379008276516720"
    },
    {
      "address": "axav4h5SHghGAdMGQ4NYU6bUf9SGAxhsNt66LaUG6uvK361",
      "stake": "450000000000000000000",
      "reward": "122187309641904914"
    },
    {
      "address": "ayUMbHi6cAuTKSKSPNwRys91PndpqUWXSXGiY9B5nRfDmhs",
      "stake": "1066000000000000000000",
      "reward": "289448364599715502"
    },
    {
      "address": "ayfhRN7demZsEeW3Yptk2g5tDUWqfCBQYKKZRcuBSRqrnaF",
      "stake": "200000000000000000000",
      "reward": "54305530378056795"
    },
    {
      "address": "b1asNYQwy2Abs8f9HCnEsbDjVYfeu7KQKFme95jbtgTmucm",
      "stake": "1000000000000000000000",
      "reward": "271527651890283974"
    },
    {
      "address": "b1bQqH1HzQ9Y6q4eun2H5rqqL883Fp5kUHVxaX56FDMjCXS",
      "stake": "146908298286466182295",
      "reward": "39889590712613234"
    },
    {
      "address": "b1nYHE2F1MN6VxpVaH58Rg5PjjmTXduP54CNqkYmqgpK7ET",
      "stake": "99990000000000000000000",
      "reward": "27150051436788935370"
    },
    {
      "address": "b1pzCtzg6YDWpb8zRgojfHMqFRg8VJuqC76aaiumm1kHRHx",
      "stake": "200000000000000000000",
      "reward": "54305530378056795"
    },
    {
      "address": "b28fEyUVECCqM13pKNvq54SgiAaiy9e1S3mbxUoXH5VVQ8z",
      "stake": "200000000000000000000",
      "reward": "54305530378056795"
    },
    {
      "address": "b3hcNzmuXGQcJfH6HiCxELAbjtUQshmkDr2zpYu6wQKv8QP",
      "stake": "255000000000000000000",
      "reward": "69239457635916401"
    },
    {
      "address": "b4RfDSNQmWmbA4NTK3k8y1AqzXEMfhzPkZj7J9kRDfgLsqx",
      "stake": "1850000000000000000000",
      "reward": "502326022288302478"
    },
    {
      "address": "b4ZtQqAe48wHGG1JsJ8oSWF8jMagL7wLzncGZHBUhzWSE2L",
      "stake": "180000000000000000000",
      "reward": "48874816889783666"
    },
    {
      "address": "b75k23ULgwg2Pu3GEYAvY3L9uJYeurdCC4pdQqivbfjwf2Z",
      "stake": "1160000000000000000000",
      "reward": "314972022709240260"
    },
    {
      "address": "b7YKxJqaedHMS3KmPEUbEAeWocE1CnjFKUHxGAk1ajPEcHM",
      "stake": "100000000000000000000",
      "reward": "27152765189028397"
    },
    {
      "address": "b8uBGf2oW1xoXv49ZuPCJQfRuLH1Sa8CFykNJ1jAvsxza42",
      "stake": "105000000000000000000",
      "reward": "28510176143650931"
    },
    {
      "address": "b96zDAz7v5WyWKdK4PvCNtJHrCNYcjPvFxRMpsKJCnooDUx",
      "stake": "1529710502598740858081",
      "reward": "415358659921339665"
    },
    {
      "address": "b9B51gLV1CJ7RWBN4HSqgdBwZwt8Ukd2wzBhaTdJgxs2SGQ",
      "stake": "162900000000000000000",
      "reward": "44231647779241695"
    },
    {
      "address": "b9QJXbX3rjah9dYcnoU9sbCbw24ZRWBZYBJn5sfwRoGBA6K",
      "stake": "123549564502114936636",
      "reward": "33546983734335606"
    },
    {
      "address": "b9aGKqgox2nBrmUknhLXXnkhD1tDjjGMYPqJ2j1zjXSr9pV",
      "stake": "109044579524210232540",
      "reward": "29608459593342566"
    },
    {
      "address": "b9fT5KG8xskFTq2mW6BpGE8vjqV4emWsLzFW77YeZeqhRhp",
      "stake": "100000000000000000000",
      "reward": "27152765189028397"
    },
    {
      "address": "b9mrNvzFb6tWwdxa7AwNBBeCynGKZt9LMT4gZcYFBb4RaLS",
      "stake": "4940000000000000000000",
      "reward": "1341346653821491983"
    },
    {
      "address": "b9tRH9HWmZgvACdmCPcwbMPu8WxawaCVJkhqpCtAXNfhYtX",
      "stake": "100000000000000000000",
      "reward": "27152765189028397"
    },
    {
      "address": "b9we8poPDktHNVtf76qHPcn4CQThg4tRCm4vvv9jLHPRiHy",
      "stake": "458000000000000000000",
      "reward": "124359541553725016"
    },
    {
      "address": "bA5d8sGB2V57f4ki81GkBcq5GesTeT1t46CJk8rUWks5cJd",
      "stake": "100000000000000000000",
      "reward": "27152765189028397"
    },
    {
      "address": "bBsQtRSKtdjuJ6L6iJwcm7necLEHfVEttWwUopaFBfKFrne",
      "stake": "200000000000000000000",
      "reward": "54305530378056795"
    },
    {
      "address": "bC2ma83QSkLPxHJxvVhGggcbyaAyhqDzmmQm1UkZLovfAtB",
      "stake": "100000000000000000000",
      "reward": "27152765189028397"
    },
    {
      "address": "bCSs21oEx6QTkEQRfbW2mGaAHLCf2Sk6kkZj7FYJ2qw5Bno",
      "stake": "191500000000000000000",
      "reward": "51997450403796140"
    },
    {
      "address": "bCdE9oitEmUHHuSgEHJ7YsRPb31i2VE7bkfPEck2oJovnYE",
      "stake": "1569739455169200722131",
      "reward": "426227574586366898"
    },
    {
      "address": "bEEzUR9yqHhVfF7nJZxk1PYQhTkJb6FVQg2f2axPvisi8xr",
      "stake": "123000000000000000000",
      "reward": "33397764799607597"
    },
    {
      "address": "bEbSVkacUTzXJjcf9TMrkEbfF6HuYsx2VSirsKsXWeSDNx9",
      "stake": "482000000000000000000",
      "reward": "130876237289185321"
    },
    {
      "address": "bEvKwgVQakqdoCHT2dncrxVc7AZtJKh6eCpLBehKfLmRXib",
      "stake": "100000000000000000000",
      "reward": "27152765189028397"
    },
    {
      "address": "bF7rKmsYihz6d6UkPrY9p7CEpgT7ssj2s6rpSExySZbMb5h",
      "stake": "100000000000000000000",
      "reward": "27152765189028397"
    },
    {
      "address": "bFMdD6UhLDFxmzRbMA5f4zthuE3AT1FhJ4kknm6dcThUavC",
      "stake": "4501101019389508642518",
      "reward": "1222173406210625401"
    },
    {
      "address": "bFR6SwiaFq8g5DGVyJhj4oeJYLNzcrvHpFR6taBpkq1eQZJ",
      "stake": "110000000000000000000",
      "reward": "29867854515719213"
    },
    {
      "address": "bGzQUyMYwTFbhofX6CjQ8oft47S2ogFhFHo9Bfttw1mRzVv",
      "stake": "200000000000000000000",
      "reward": "54305530378056795"
    },
    {
      "address": "bHGHtTrxphYqDVGxSqrMdN6zyQoVV3egmLt5aiDfma8nyft",
      "stake": "100000000000000000000",
      "reward": "27152765189028397"
    },
    {
      "address": "bHfbWPTvo2stTdo9ezuk7fywUgADBGLbMrG7sE3qJxtsjoK",
      "stake": "200000000000000000000",
      "reward": "54305530378056795"
    },
    {
      "address": "bHnuuCekky37vvG2fpk53hyPt3j6gm1XjrbgUwdrzM3L1eT",
      "stake": "500000000000000000000",
      "reward": "135763825945141987"
    },
    {
      "address": "bHsYgVwCaBEoaPUWdsafEwi4QDs4bu8awexV9XgKihsZjcv",
      "stake": "100000000000000000000",
      "reward": "27152765189028397"
    },
    {
      "address": "bJ2zGQHiH2PPXGR2q8eCJM2n9iM8gG2ecAhdopHrYt4ziFe",
      "stake": "1013000000000000000000",
      "reward": "275057294756726609"
    },
    {
      "address": "bKXSASCX1V4YB29zPuyAXzzUT5EJenBhDkZsak22mXy39Qm",
      "stake": "15214759938456816809845",
      "reward": "4131228093991758472"
    },
    {
      "address": "bL6QnUXiVWrcG8uLrWEiFngwVEyBW25iM2QJa4JAq9bMJyJ",
      "stake": "5600000000000000000000",
      "reward": "1520554850585590257"
    },
    {
      "address": "bLEBuJJEMNFQAWYovsXxkM9iebRzjn5rc2GxY6Ekz91f3uA",
      "stake": "500000000000000000000",
      "reward": "135763825945141987"
    },
    {
      "address": "bLS4AXmmFSVnXWauycZqW8c3cZLFU71eXtTSRSfrZoQDChQ",
      "stake": "400000000000000000000",
      "reward": "108611060756113590"
    },
    {
      "address": "bMzk8JW12iwnyQVFEF91SZmCpEMoARTsdzzydHqaaTkziZS",
      "stake": "101000000000000000000",
      "reward": "27424193896463754"
    },
    {
      "address": "bNYDFbCSPn5hZS3ZdeCh8x1TYhq93qqzndqU6dyGxnoZ669",
      "stake": "764104204158747656473",
      "reward": "207475290449563254"
    },
    {
      "address": "bNdDRUMBPT8YU1hDjg3YoDPvLNWLmAg8EQPB4ULEDepJTTY",
      "stake": "10240495114819344578385",
      "reward": "2780577719815208855"
    },
    {
      "address": "bPBhdJDZWqqgn2VFh3jBbxnJA4QKNi5NS6p3ooih4ZnpYsA",
      "stake": "199998382294395882563",
      "reward": "54304995543165297"
    },
    {
      "address": "bQjp14qUQTXuT7Wq7wdTthc2cdkHtp7NgiE18vycMhyPHxv",
      "stake": "245000000000000000000",
      "reward": "66524100891779837"
    },
    {
      "address": "bR5wnfs4CLbq1sJhwNqGLEtto6bZ7eSnpxtuoJMLftbZU7S",
      "stake": "126386617832737941980",
      "reward": "34317413395538820"
    },
    {
      "address": "bRkPqDaAiFgnti4NHfrGxpVSSBfAh3fxpBe3rBw1Sd9iHG2",
      "stake": "100000000000000000000",
      "reward": "27152765189028397"
    },
    {
      "address": "bTMXt97vjoW9nEx8FRPbf6EPa9vUnwra9EjdB3FcjSgV7NY",
      "stake": "1100000000000000000000",
      "reward": "298680417079312372"
    },
    {
      "address": "bTsu9h8wBpmNeBqieyeMjNkVnHQzbnfEKGFEgTLxWTraNfC",
      "stake": "1000000000000000000000",
      "reward": "271527651890283974"
    },
    {
      "address": "bUFtTzuG63wnjhgKB3xANagEXanSMjrLXSUo5xwuwYiPS7r",
      "stake": "100000000000000000000",
      "reward": "27152765189028397"
    },
    {
      "address": "bVsRszEJ6UQhq3wTyR6CoSc9EnVXpwBauP59PabbpgK5qsA",
      "stake": "156120000000000000000",
      "reward": "42390746082704753"
    },
    {
      "address": "bW3WyTYQ5Rrvi5mLqCbL9aLY8MMy4iNCTM2H5ZPJ6QXdm8Y",
      "stake": "100000000000000000000",
      "reward": "27152765189028397"
    },
    {
      "address": "bWuixgswMhku2BbdAMwwfHTg7171RXYeDFsubSXsW7KfKj3",
      "stake": "332104285186157461324",
      "reward": "90175302046169257"
    },
    {
      "address": "bYcsVoybaf8hTZEEmRD78XvtGJirsuK3NYdEjj6a3JC78HU",
      "stake": "187000000000000000000",
      "reward": "50775620094168411"
    },
    {
      "address": "bZ8Axxe1tmVW3mb2tPNtuPGBGYr1Dqdx1r4QLuJDvN1qGVN",
      "stake": "1200000000000000000000",
      "reward": "325833182268340769"
    },
    {
      "address": "bZNB7zMdttmYVqDTDsUPrWWsi9CteX7md5KH2BayNqBPno2",
      "stake": "137957820631484724890",
      "reward": "37459300965645231"
    },
    {
      "address": "bZVu8dNSRdzyVku8iVjNtXiE8hQP7DjzLvksyyR1y8aJuN1",
      "stake": "352393766035467218798",
      "reward": "95684636263492627"
    },
    {
      "address": "bZdnNaAhYFE5ewerBSiqeBYuiXNPCgoSPqKsZWd6H5uEEdr",
      "stake": "2740000000000000000000",
      "reward": "743985552245421491"
    },
    {
      "address": "bbhwxw2hLYGqXJN4RpgSoJrvcyt4Ze5GDuFTtcA18sMPcrU",
      "stake": "210000000000000000000",
      "reward": "57020619704747610"
    },
    {
      "address": "bbvjNHmVw5mx8wDKgh2n8BZwfSyFntaptdPn2Tai1d9YCLf",
      "stake": "1000000000000000000000",
      "reward": "271527651890283974"
    },
    {
      "address": "bc5WVhbqYRbSs4T2WUgHsKfj2eQMJdDSYnyjV635NR752rV",
      "stake": "12667656323541542734820",
      "reward": "3439618922670759625"
    },
    {
      "address": "bcPnVn4AXMxxQCURzYLS7E8C564pKPF8K1upv5FUMhVk16c",
      "stake": "100072857289301282859",
      "reward": "27172286662568083"
    },
    {
      "address": "beiCTs5cPPjUA78JYqNQhmSm9FP8mGsmsdLC4waFQGHjSCk",
      "stake": "200000000000000000000",
      "reward": "54305530378056795"
    },
    {
      "address": "bgMASgs7grDHHLcNtHgd8jhJrraRuzP9hWmLJwz7HJFuBbf",
      "stake": "750000000000000000000",
      "reward": "203645605208990106"
    },
    {
      "address": "bgsyE7ppvEGiMTp8Rb8Zt14kvj9DjoEDfSKwCwpf2q9PZEa",
      "stake": "123553312928522186378",
      "reward": "33548053404118602"
    },
    {
      "address": "bh1wK1j613JCcRKqYXZxX4ufvDcMy5XSRSNPm4dYH5spdk1",
      "stake": "2102415600000000000000",
      "reward": "570863776546573188"
    },
    {
      "address": "bhLkxrRDRQnjNCVz5RNFfJpGAroyPw33it28MenNQMbMcJn",
      "stake": "4200000000000000000000",
      "reward": "1140416137939192692"
    },
    {
      "address": "bhXHQBFo8TWnRfAySYNW6Fg17N6dDRRYek8HTRZiSzp7DXD",
      "stake": "500000000000000000000",
      "reward": "135763825945141987"
    }
  ]
}
